Workbook

Sheet Loan_Portfolio
A1: Loan_ID | B1: Branch | C1: Region | D1: Product_Type | E1: Borrower_Segment | F1: Loan_Amount (₹) | G1: Loan_Tenor (months) | H1: Interest_Rate (%) | I1: EMI (₹) | J1: Outstanding_Balance (₹) | K1: Months_Overdue | L1: Credit_Score | M1: Collateral_Type | N1: Relationship_Manager | O1: Disbursement_Month | P1: NPA Flag | Q1: Risk Behaviour | R1: RM Commission Rate | S1: Priority Review | T1: Rate Concession Eligible | U1: Loan Coverage Ratio
A2: L001 | B2: Mumbai Central | C2: West | D2: Home Loan | E2: Salaried | F2: 0 | G2: 240 | H2: 8.5 | I2: 65217 | J2: 6980000 | K2: 0 | L2: 762 | M2: Property | N2: Ravi Sharma | O2: Apr-23 | P2: =IF(K2>=6, "Flagged", "") | Q2: {=_xlfn.IFS(L2>=780, "Prime", L2>=700, "Near Prime", L2>=640, "Sub Prime", L2<640, "High Risk")} -> Near Prime | R2: {=_xlfn.IFS(D2="Home Loan",F2*0.005,D2="Business Loan",F2*0.0075,D2="Auto Loan",F2*0.004,D2="Personal Loan",F2*0.006)} -> 0 | S2: =IF(OR(K2>=3, L2<650), "YES", "NO") -> NO | T2: =IF(AND(OR(D2="Home Loan", D2="Auto Loan"), E2="Salaried", L2>=750), "Eligible", "Not Eligible") -> Eligible | U2: =IFERROR(J2/F2, "NA") -> NA
A3: L002 | B3: Chennai South | C3: South | D3: Personal Loan | E3: Salaried | F3: 450000 | G3: 36 | H3: 14 | I3: 15364 | J3: 312000 | K3: 0 | L3: 710 | M3: None | N3: Priya Nair | O3: May-23 | P3: =IF(K3>=6, "Flagged", "") | Q3: {=_xlfn.IFS(L3>=780, "Prime", L3>=700, "Near Prime", L3>=640, "Sub Prime", L3<640, "High Risk")} -> Near Prime | R3: {=_xlfn.IFS(D3="Home Loan",F3*0.005,D3="Business Loan",F3*0.0075,D3="Auto Loan",F3*0.004,D3="Personal Loan",F3*0.006)} -> 2700 | S3: =IF(OR(K3>=3, L3<650), "YES", "NO") -> NO | T3: =IF(AND(OR(D3="Home Loan", D3="Auto Loan"), E3="Salaried", L3>=750), "Eligible", "Not Eligible") -> Not Eligible | U3: =IFERROR(J3/F3, "NA") -> 0.69333333
A4: L003 | B4: Delhi North | C4: North | D4: Business Loan | E4: Self-Emp | F4: 2500000 | G4: 60 | H4: 11.5 | I4: 54793 | J4: 1980000 | K4: 2 | L4: 684 | M4: Machinery | N4: Amit Gupta | O4: Jun-23 | P4: =IF(K4>=6, "Flagged", "") | Q4: {=_xlfn.IFS(L4>=780, "Prime", L4>=700, "Near Prime", L4>=640, "Sub Prime", L4<640, "High Risk")} -> Sub Prime | R4: {=_xlfn.IFS(D4="Home Loan",F4*0.005,D4="Business Loan",F4*0.0075,D4="Auto Loan",F4*0.004,D4="Personal Loan",F4*0.006)} -> 18750 | S4: =IF(OR(K4>=3, L4<650), "YES", "NO") -> NO | T4: =IF(AND(OR(D4="Home Loan", D4="Auto Loan"), E4="Salaried", L4>=750), "Eligible", "Not Eligible") -> Not Eligible | U4: =IFERROR(J4/F4, "NA") -> 0.792
A5: L004 | B5: Kolkata East | C5: East | D5: Home Loan | E5: Salaried | F5: 5200000 | G5: 180 | H5: 8.75 | I5: 52019 | J5: 4870000 | K5: 0 | L5: 785 | M5: Property | N5: Sneha Das | O5: Apr-23 | P5: =IF(K5>=6, "Flagged", "") | Q5: {=_xlfn.IFS(L5>=780, "Prime", L5>=700, "Near Prime", L5>=640, "Sub Prime", L5<640, "High Risk")} -> Prime | R5: {=_xlfn.IFS(D5="Home Loan",F5*0.005,D5="Business Loan",F5*0.0075,D5="Auto Loan",F5*0.004,D5="Personal Loan",F5*0.006)} -> 26000 | S5: =IF(OR(K5>=3, L5<650), "YES", "NO") -> NO | T5: =IF(AND(OR(D5="Home Loan", D5="Auto Loan"), E5="Salaried", L5>=750), "Eligible", "Not Eligible") -> Eligible | U5: =IFERROR(J5/F5, "NA") -> 0.93653846
A6: L005 | B6: Mumbai Central | C6: West | D6: Auto Loan | E6: Salaried | F6: 800000 | G6: 60 | H6: 9.25 | I6: 16656 | J6: 620000 | K6: 1 | L6: 730 | M6: Vehicle | N6: Ravi Sharma | O6: Jul-23 | P6: =IF(K6>=6, "Flagged", "") | Q6: {=_xlfn.IFS(L6>=780, "Prime", L6>=700, "Near Prime", L6>=640, "Sub Prime", L6<640, "High Risk")} -> Near Prime | R6: {=_xlfn.IFS(D6="Home Loan",F6*0.005,D6="Business Loan",F6*0.0075,D6="Auto Loan",F6*0.004,D6="Personal Loan",F6*0.006)} -> 3200 | S6: =IF(OR(K6>=3, L6<650), "YES", "NO") -> NO | T6: =IF(AND(OR(D6="Home Loan", D6="Auto Loan"), E6="Salaried", L6>=750), "Eligible", "Not Eligible") -> Not Eligible | U6: =IFERROR(J6/F6, "NA") -> 0.775
A7: L006 | B7: Hyderabad | C7: South | D7: Personal Loan | E7: Self-Emp | F7: 350000 | G7: 24 | H7: 15.5 | I7: 17139 | J7: 89000 | K7: 0 | L7: 695 | M7: None | N7: Kiran Reddy | O7: Aug-23 | P7: =IF(K7>=6, "Flagged", "") | Q7: {=_xlfn.IFS(L7>=780, "Prime", L7>=700, "Near Prime", L7>=640, "Sub Prime", L7<640, "High Risk")} -> Sub Prime | R7: {=_xlfn.IFS(D7="Home Loan",F7*0.005,D7="Business Loan",F7*0.0075,D7="Auto Loan",F7*0.004,D7="Personal Loan",F7*0.006)} -> 2100 | S7: =IF(OR(K7>=3, L7<650), "YES", "NO") -> NO | T7: =IF(AND(OR(D7="Home Loan", D7="Auto Loan"), E7="Salaried", L7>=750), "Eligible", "Not Eligible") -> Not Eligible | U7: =IFERROR(J7/F7, "NA") -> 0.25428571
A8: L007 | B8: Delhi North | C8: North | D8: Business Loan | E8: Self-Emp | F8: 8000000 | G8: 84 | H8: 12 | I8: 133676 | J8: 6700000 | K8: 4 | L8: 641 | M8: Property | N8: Amit Gupta | O8: Sep-23 | P8: =IF(K8>=6, "Flagged", "") | Q8: {=_xlfn.IFS(L8>=780, "Prime", L8>=700, "Near Prime", L8>=640, "Sub Prime", L8<640, "High Risk")} -> Sub Prime | R8: {=_xlfn.IFS(D8="Home Loan",F8*0.005,D8="Business Loan",F8*0.0075,D8="Auto Loan",F8*0.004,D8="Personal Loan",F8*0.006)} -> 60000 | S8: =IF(OR(K8>=3, L8<650), "YES", "NO") -> YES | T8: =IF(AND(OR(D8="Home Loan", D8="Auto Loan"), E8="Salaried", L8>=750), "Eligible", "Not Eligible") -> Not Eligible | U8: =IFERROR(J8/F8, "NA") -> 0.8375
A9: L008 | B9: Bangalore | C9: South | D9: Home Loan | E9: Salaried | F9: 6800000 | G9: 240 | H9: 8.25 | I9: 58012 | J9: 6540000 | K9: 0 | L9: 798 | M9: Property | N9: Meena Iyer | O9: Apr-23 | P9: =IF(K9>=6, "Flagged", "") | Q9: {=_xlfn.IFS(L9>=780, "Prime", L9>=700, "Near Prime", L9>=640, "Sub Prime", L9<640, "High Risk")} -> Prime | R9: {=_xlfn.IFS(D9="Home Loan",F9*0.005,D9="Business Loan",F9*0.0075,D9="Auto Loan",F9*0.004,D9="Personal Loan",F9*0.006)} -> 34000 | S9: =IF(OR(K9>=3, L9<650), "YES", "NO") -> NO | T9: =IF(AND(OR(D9="Home Loan", D9="Auto Loan"), E9="Salaried", L9>=750), "Eligible", "Not Eligible") -> Eligible | U9: =IFERROR(J9/F9, "NA") -> 0.96176471
A10: L009 | B10: Mumbai Central | C10: West | D10: Personal Loan | E10: Salaried | F10: 600000 | G10: 48 | H10: 13.5 | I10: 17203 | J10: 410000 | K10: 0 | L10: 745 | M10: None | N10: Ravi Sharma | O10: Oct-23 | P10: =IF(K10>=6, "Flagged", "") | Q10: {=_xlfn.IFS(L10>=780, "Prime", L10>=700, "Near Prime", L10>=640, "Sub Prime", L10<640, "High Risk")} -> Near Prime | R10: {=_xlfn.IFS(D10="Home Loan",F10*0.005,D10="Business Loan",F10*0.0075,D10="Auto Loan",F10*0.004,D10="Personal Loan",F10*0.006)} -> 3600 | S10: =IF(OR(K10>=3, L10<650), "YES", "NO") -> NO | T10: =IF(AND(OR(D10="Home Loan", D10="Auto Loan"), E10="Salaried", L10>=750), "Eligible", "Not Eligible") -> Not Eligible | U10: =IFERROR(J10/F10, "NA") -> 0.68333333
A11: L010 | B11: Kolkata East | C11: East | D11: Auto Loan | E11: Salaried | F11: 950000 | G11: 60 | H11: 9.75 | I11: 20163 | J11: 760000 | K11: 3 | L11: 668 | M11: Vehicle | N11: Sneha Das | O11: Nov-23 | P11: =IF(K11>=6, "Flagged", "") | Q11: {=_xlfn.IFS(L11>=780, "Prime", L11>=700, "Near Prime", L11>=640, "Sub Prime", L11<640, "High Risk")} -> Sub Prime | R11: {=_xlfn.IFS(D11="Home Loan",F11*0.005,D11="Business Loan",F11*0.0075,D11="Auto Loan",F11*0.004,D11="Personal Loan",F11*0.006)} -> 3800 | S11: =IF(OR(K11>=3, L11<650), "YES", "NO") -> YES | T11: =IF(AND(OR(D11="Home Loan", D11="Auto Loan"), E11="Salaried", L11>=750), "Eligible", "Not Eligible") -> Not Eligible | U11: =IFERROR(J11/F11, "NA") -> 0.8
A12: L011 | B12: Chennai South | C12: South | D12: Business Loan | E12: Self-Emp | F12: 3500000 | G12: 60 | H12: 12.5 | I12: 79066 | J12: 2900000 | K12: 0 | L12: 712 | M12: Machinery | N12: Priya Nair | O12: Apr-23 | P12: =IF(K12>=6, "Flagged", "") | Q12: {=_xlfn.IFS(L12>=780, "Prime", L12>=700, "Near Prime", L12>=640, "Sub Prime", L12<640, "High Risk")} -> Near Prime | R12: {=_xlfn.IFS(D12="Home Loan",F12*0.005,D12="Business Loan",F12*0.0075,D12="Auto Loan",F12*0.004,D12="Personal Loan",F12*0.006)} -> 26250 | S12: =IF(OR(K12>=3, L12<650), "YES", "NO") -> NO | T12: =IF(AND(OR(D12="Home Loan", D12="Auto Loan"), E12="Salaried", L12>=750), "Eligible", "Not Eligible") -> Not Eligible | U12: =IFERROR(J12/F12, "NA") -> 0.82857143
A13: L012 | B13: Hyderabad | C13: South | D13: Home Loan | E13: Salaried | F13: 4200000 | G13: 180 | H13: 8.9 | I13: 42471 | J13: 3950000 | K13: 0 | L13: 776 | M13: Property | N13: Kiran Reddy | O13: May-23 | P13: =IF(K13>=6, "Flagged", "") | Q13: {=_xlfn.IFS(L13>=780, "Prime", L13>=700, "Near Prime", L13>=640, "Sub Prime", L13<640, "High Risk")} -> Near Prime | R13: {=_xlfn.IFS(D13="Home Loan",F13*0.005,D13="Business Loan",F13*0.0075,D13="Auto Loan",F13*0.004,D13="Personal Loan",F13*0.006)} -> 21000 | S13: =IF(OR(K13>=3, L13<650), "YES", "NO") -> NO | T13: =IF(AND(OR(D13="Home Loan", D13="Auto Loan"), E13="Salaried", L13>=750), "Eligible", "Not Eligible") -> Eligible | U13: =IFERROR(J13/F13, "NA") -> 0.94047619
... A51: L050 | B51: Bangalore | C51: South | D51: Home Loan | E51: Salaried | F51: 5900000 | G51: 240 | H51: 8.45 | I51: 51648 | J51: 5670000 | K51: 0 | L51: 794 | M51: Property | N51: Meena Iyer | O51: Dec-23 | P51: =IF(K51>=6, "Flagged", "") | Q51: {=_xlfn.IFS(L51>=780, "Prime", L51>=700, "Near Prime", L51>=640, "Sub Prime", L51<640, "High Risk")} -> Prime | R51: {=_xlfn.IFS(D51="Home Loan",F51*0.005,D51="Business Loan",F51*0.0075,D51="Auto Loan",F51*0.004,D51="Personal Loan",F51*0.006)} -> 29500 | S51: =IF(OR(K51>=3, L51<650), "YES", "NO") -> NO | T51: =IF(AND(OR(D51="Home Loan", D51="Auto Loan"), E51="Salaried", L51>=750), "Eligible", "Not Eligible") -> Eligible | U51: =IFERROR(J51/F51, "NA") -> 0.96101695

Sheet Analysis_Workspace
A1: IndiaFirst Commercial Bank — Analysis Workspace (Students complete this sheet)
A2: Q# | B2: Metric / Question | C2: Your Formula / Answer | D2: Formula
A3: ── PART A: Basic Conditional Counting & Summation ──
A4: Q1 | B4: Count the total number of Home Loan accounts in the portfolio. | C4: =COUNTIF(Loan_Portfolio!D2:D51, "Home Loan") -> 15 | D4: =_xlfn.FORMULATEXT(C4) -> =COUNTIF(Loan_Portfolio!D2:D51, "Home Loan")
A5: Q2 | B5: Calculate the total outstanding balance of all loans disbursed from the South region. | C5: =SUMIF(Loan_Portfolio!C2:C51, "South", Loan_Portfolio!J2:J51) -> 68244000 | D5: =_xlfn.FORMULATEXT(C5) -> =SUMIF(Loan_Portfolio!C2:C51, "South", Loan_Portfolio!J2:J51)
A6: Q3 | B6: Find the average interest rate applicable to Self-Employed borrowers only. | C6: =AVERAGEIF(Loan_Portfolio!E2:E51, "Self-Emp", Loan_Portfolio!H2:H51) -> 12.205882 | D6: =_xlfn.FORMULATEXT(C6) -> =AVERAGEIF(Loan_Portfolio!E2:E51, "Self-Emp", Loan_Portfolio!H2:H51)
A7: Q4 | B7: Count the number of loans where the borrower has a Credit Score above 750. | C7: =COUNTIF(Loan_Portfolio!L2:L51, ">750") -> 20 | D7: =_xlfn.FORMULATEXT(C7) -> =COUNTIF(Loan_Portfolio!L2:L51, ">750")
A8: Q5 | B8: Calculate the total Loan Amount sanctioned by Relationship Manager 'Ravi Sharma'. | C8: =SUMIF(Loan_Portfolio!N2:N51, "Ravi Sharma", Loan_Portfolio!F2:F51) -> 29750000 | D8: =_xlfn.FORMULATEXT(C8) -> =SUMIF(Loan_Portfolio!N2:N51, "Ravi Sharma", Loan_Portfolio!F2:F51)
A9: ── PART B: Multi-Condition Analysis (SUMIFS / COUNTIFS / AVERAGEIFS) ──
A10: Q6 | B10: How many Business Loans were sanctioned to Self-Employed borrowers in the North or West region? (Hint: may need two formulas combined) | C10: =COUNTIFS(Loan_Portfolio!C2:C51,"North",Loan_Portfolio!E2:E51,"Self-Emp",Loan_Portfolio!D2:D51,"Business Loan")+COUNTIFS(Loan_Portfolio!C2:C51,"West",Loan_Portfolio!E2:E51,"Self-Emp",Loan_Portfolio!D2:D51,"Business Loan") -> 4 | D10: =_xlfn.FORMULATEXT(C10) -> =COUNTIFS(Loan_Portfolio!C2:C51,"North",Loan_Portfolio!E2:E51,"Self-Emp",Loan_Portfolio!D2:D51,"Business Loan")+COUNTIFS(Loan_Portfolio!C2:C51,"West",Loan_Portfolio!E2:E51,"Self-Emp",Loan_Portfolio!D2:D51,"Business Loan")
A11: Q7 | B11: What is the total outstanding balance of Home Loans where the borrower is Salaried AND the credit score is 750 or above? | C11: =SUMIFS(Loan_Portfolio!J2:J51, Loan_Portfolio!D2:D51, "Home Loan", Loan_Portfolio!E2:E51, "Salaried", Loan_Portfolio!L2:L51, ">750") -> 74210000 | D11: =_xlfn.FORMULATEXT(C11) -> =SUMIFS(Loan_Portfolio!J2:J51, Loan_Portfolio!D2:D51, "Home Loan", Loan_Portfolio!E2:E51, "Salaried", Loan_Portfolio!L2:L51, ">750")
A12: Q8 | B12: Find the average EMI for Auto Loans disbursed in the West region. | C12: =AVERAGEIFS(Loan_Portfolio!I2:I51, Loan_Portfolio!C2:C51, "West", Loan_Portfolio!D2:D51, "Auto Loan") -> 23565.667 | D12: =_xlfn.FORMULATEXT(C12) -> =AVERAGEIFS(Loan_Portfolio!I2:I51, Loan_Portfolio!C2:C51, "West", Loan_Portfolio!D2:D51, "Auto Loan")
A13: Q9 | B13: How many loans have an outstanding balance greater than ₹50,00,000 AND have zero months overdue? | C13: =COUNTIFS(Loan_Portfolio!J2:J51, ">5000000", Loan_Portfolio!K2:K51, "0") -> 10 | D13: =_xlfn.FORMULATEXT(C13) -> =COUNTIFS(Loan_Portfolio!J2:J51, ">5000000", Loan_Portfolio!K2:K51, "0")
A14: Q10 | B14: What is the total loan amount sanctioned for Personal Loans with a credit score between 700 and 750 (inclusive)? | C14: =COUNTIFS(Loan_Portfolio!J3:J52, ">5000000", Loan_Portfolio!K3:K52, "0") -> 9 | D14: =_xlfn.FORMULATEXT(C14) -> =COUNTIFS(Loan_Portfolio!J3:J52, ">5000000", Loan_Portfolio!K3:K52, "0")
A15: ── PART C: Nested IF & IFS — Risk Classification ──
A16: Q11 | B16: In column P of the Loan_Portfolio sheet (header: NPA_Flag), write a formula using IF to classify each loan: 'NPA' if Months_Overdue ≥ 6,else, 'Standard' | C16: "=IF(K2>=6, "Flagged", "Pass")" | D16: =_xlfn.FORMULATEXT(C16) -> #N/A
A17: Q12 | B17: In column Q of the Loan_Portfolio sheet (header: Risk_Band), write a formula using IFS to assign a Risk Band based on Credit_Score: 'Prime' (≥780), 'Near-Prime' (700–779), 'Sub-Prime' (640–699), 'High-Risk' (<640). | C17: "=IFS(L2>=780, "Prime", L2>=700, "Near Prime", L2>=640, "Sub Prime", L2<640, "High Risk")" | D17: =_xlfn.FORMULATEXT(C17) -> #N/A
A18: Q13 | B18: Using the IFS / nested IF logic, write a formula in column R (header: RM_Commission_Rate) of Loan_Portfolio to assign commission rates: Home Loan = 0.50%, Business Loan = 0.75%, Auto Loan = 0.40%, Personal Loan = 0.60%. | C18: "=IFS(D2="Home Loan",F2*0.005,D2="Business Loan",F2*0.0075,D2="Auto Loan",F2*0.004,D2="Personal Loan",F2*0.006)" | D18: =_xlfn.FORMULATEXT(C18) -> #N/A
A19: ── PART D: AND / OR Logic ──
A20: Q14 | B20: Count loans where the borrower is Salaried AND the product type is Home Loan AND the credit score exceeds 760. Use COUNTIFS. | C20: =COUNTIFS(Loan_Portfolio!E2:E51, "Salaried", Loan_Portfolio!D2:D51, "Home Loan", Loan_Portfolio!L2:L51, ">750") -> 13 | D20: =_xlfn.FORMULATEXT(C20) -> =COUNTIFS(Loan_Portfolio!E2:E51, "Salaried", Loan_Portfolio!D2:D51, "Home Loan", Loan_Portfolio!L2:L51, ">750")
A21: Q15 | B21: A loan qualifies for a 'Priority Review' if EITHER the Months_Overdue ≥ 3 OR the Credit Score is below 650. In column S (header: Priority_Review) of Loan_Portfolio, write a formula using IF and OR to flag these loans as 'Yes' or 'No'. | C21: "=IF(OR(K2>=3, L2<650), "YES", "NO")" | D21: =_xlfn.FORMULATEXT(C21) -> #N/A
A22: Q16 | B22: A loan is eligible for an interest rate concession only if: the borrower is Salaried AND the Credit Score is ≥ 750 AND the product is either Home Loan or Auto Loan. In column T (header: Rate_Concession_Eligible), write IF + AND + OR to output 'Eligible' or 'Not Eligible'. | C22: "=IF(AND(OR(D2="Home Loan", D2="Auto Loan"), E2="Salaried", L2>=750), "Eligible", "Not Eligible")" | D22: =_xlfn.FORMULATEXT(C22) -> #N/A
A23: ── PART E: IFERROR & Robust Formula Design ──
A24: Q17 | B24: Calculate the 'Loan Coverage Ratio' (Outstanding Balance ÷ Original Loan Amount) for each loan. In column U (header: Coverage_Ratio) of Loan_Portfolio, write a formula with IFERROR to handle any division errors — display 'N/A' if an error occurs. | C24: "=IFERROR(J2/F2, "NA")" | D24: =_xlfn.FORMULATEXT(C24) -> #N/A
A25: ── PART F: Integrative / Dashboard Metrics ──
A26: Q19 | B26: Calculate the Gross NPA Ratio: Total Outstanding Balance of NPA loans ÷ Total Outstanding Balance of all loans. Express as a percentage. (Use your NPA_Flag column from Q11.) | C26: =(SUMIFS(Loan_Portfolio!J2:J51,Loan_Portfolio!P2:P51,"Flagged")/SUM(Loan_Portfolio!J2:J51)) -> 0.030601813 | D26: =_xlfn.FORMULATEXT(C26) -> =(SUMIFS(Loan_Portfolio!J2:J51,Loan_Portfolio!P2:P51,"Flagged")/SUM(Loan_Portfolio!J2:J51))
A27: Q20 | B27: Build a mini Branch Performance Summary table (below) showing: for each of the 5 branches — (a) Total Loan Amount, (b) Count of Loans, (c) Average Credit Score, (d) Total Outstanding Balance of NPA loans only. | D27: =_xlfn.FORMULATEXT(C27) -> #N/A
A29: Branch Performance Summary Table (Enter formulas in shaded cells)
A30: Branch | B30: Total Loan Amount (₹) | C30: No. of Loans | D30: Avg. Credit Score | E30: NPA Outstanding Balance (₹)
A31: Mumbai Central | B31: =SUMIF(Loan_Portfolio!B2:B51, "Mumbai Central", Loan_Portfolio!J2:J51) -> 32630000 | C31: =COUNTIF(Loan_Portfolio!B2:B51, "Mumbai Central") -> 9 | D31: =AVERAGEIF(Loan_Portfolio!B2:B51, "Mumbai Central", Loan_Portfolio!L2:L51) -> 734.22222 | E31: =SUMIFS(Loan_Portfolio!J2:J51, Loan_Portfolio!P2:P51, "Flagged", Loan_Portfolio!B2:B51, "Mumbai Central") -> 0
A32: Chennai South | B32: =SUMIF(Loan_Portfolio!B2:B51, "Chennai South", Loan_Portfolio!J2:J51) -> 17110000 | C32: =COUNTIF(Loan_Portfolio!B2:B51, "Chennai South") -> 8 | D32: =AVERAGEIF(Loan_Portfolio!B2:B51, "Chennai South", Loan_Portfolio!L2:L51) -> 721.25 | E32: =SUMIFS(Loan_Portfolio!J2:J51, Loan_Portfolio!P2:P51, "Flagged", Loan_Portfolio!B2:B51, "Chennai South") -> 870000
A33: Delhi North | B33: =SUMIF(Loan_Portfolio!B2:B51, "Delhi North", Loan_Portfolio!J2:J51) -> 30040000 | C33: =COUNTIF(Loan_Portfolio!B2:B51, "Delhi North") -> 9 | D33: =AVERAGEIF(Loan_Portfolio!B2:B51, "Delhi North", Loan_Portfolio!L2:L51) -> 720.22222 | E33: =SUMIFS(Loan_Portfolio!J2:J51, Loan_Portfolio!P2:P51, "Flagged", Loan_Portfolio!B2:B51, "Delhi North") -> 0
A34: Kolkata East | B34: =SUMIF(Loan_Portfolio!B2:B51, "Kolkata East", Loan_Portfolio!J2:J51) -> 17770000 | C34: =COUNTIF(Loan_Portfolio!B2:B51, "Kolkata East") -> 8 | D34: =AVERAGEIF(Loan_Portfolio!B2:B51, "Kolkata East", Loan_Portfolio!L2:L51) -> 703.75 | E34: =SUMIFS(Loan_Portfolio!J2:J51, Loan_Portfolio!P2:P51, "Flagged", Loan_Portfolio!B2:B51, "Kolkata East") -> 2700000
A35: Hyderabad | B35: =SUMIF(Loan_Portfolio!B2:B51, "Hyderabad", Loan_Portfolio!J2:J51) -> 18954000 | C35: =COUNTIF(Loan_Portfolio!B2:B51, "Hyderabad") -> 8 | D35: =AVERAGEIF(Loan_Portfolio!B2:B51, "Hyderabad", Loan_Portfolio!L2:L51) -> 725.75 | E35: =SUMIFS(Loan_Portfolio!J2:J51, Loan_Portfolio!P2:P51, "Flagged", Loan_Portfolio!B2:B51, "Hyderabad") -> 0
B37: =_xlfn.FORMULATEXT(B35) -> =SUMIF(Loan_Portfolio!B2:B51, "Hyderabad", Loan_Portfolio!J2:J51) | C37: =_xlfn.FORMULATEXT(C35) -> =COUNTIF(Loan_Portfolio!B2:B51, "Hyderabad") | D37: =_xlfn.FORMULATEXT(D35) -> =AVERAGEIF(Loan_Portfolio!B2:B51, "Hyderabad", Loan_Portfolio!L2:L51) | E37: =_xlfn.FORMULATEXT(E35) -> =SUMIFS(Loan_Portfolio!J2:J51, Loan_Portfolio!P2:P51, "Flagged", Loan_Portfolio!B2:B51, "Hyderabad")

Sheet Data_Dictionary
A1: Data Dictionary — Loan_Portfolio Sheet
A2: Column Name | B2: Data Type | C2: Description | D2: Possible Values / Range
A3: Loan_ID | B3: Text | C3: Unique identifier for each loan account | D3: L001 – L050
A4: Branch | B4: Text | C4: Branch where the loan was originated | D4: Mumbai Central, Chennai South, Delhi North, Kolkata East, Hyderabad
A5: Region | B5: Text | C5: Geographic region of the branch | D5: North, South, East, West
A6: Product_Type | B6: Text | C6: Category of loan product | D6: Home Loan, Business Loan, Auto Loan, Personal Loan
A7: Borrower_Segment | B7: Text | C7: Employment profile of the borrower | D7: Salaried, Self-Emp
A8: Loan_Amount (₹) | B8: Number | C8: Original principal amount sanctioned | D8: Varies — ₹2,50,000 to ₹1,20,00,000
A9: Loan_Tenor (months) | B9: Number | C9: Total repayment period in months | D9: 24 to 300 months
A10: Interest_Rate (%) | B10: Number | C10: Annual interest rate applicable | D10: 8.25% to 16.00%
A11: EMI (₹) | B11: Number | C11: Equated Monthly Instalment payable | D11: Calculated based on loan, rate, tenor
A12: Outstanding_Balance (₹) | B12: Number | C12: Remaining principal as at March 2024 | D12: Less than or equal to Loan_Amount
A13: Months_Overdue | B13: Number | C13: Number of months EMI is overdue (0 = current) | D13: 0 to 8
... A17: Disbursement_Month | B17: Text | C17: Month-Year when loan was disbursed | D17: Apr-23 to Mar-24
