Workbook

Sheet Product_Master
A1: ZenithMart Pvt. Ltd. — Product Master Table
A2: Product_ID | B2: Product_Name | C2: Category | D2: Unit_Cost (₹) | E2: Selling_Price (₹) | F2: Supplier_ID
A3: P001 | B3: Basmati Rice 5kg | C3: Staples | D3: 220 | E3: 310 | F3: S101
A4: P002 | B4: Toor Dal 1kg | C4: Staples | D4: 110 | E4: 155 | F4: S101
A5: P003 | B5: Sunflower Oil 1L | C5: Edible Oils | D5: 145 | E5: 195 | F5: S102
A6: P004 | B6: Coconut Oil 500ml | C6: Edible Oils | D6: 180 | E6: 240 | F6: S103
A7: P005 | B7: Colgate Toothpaste 200g | C7: Personal Care | D7: 65 | E7: 95 | F7: S104
A8: P006 | B8: Dove Soap 100g | C8: Personal Care | D8: 48 | E8: 75 | F8: S104
A9: P007 | B9: Notebook 200 pages | C9: Stationery | D9: 40 | E9: 70 | F9: S105
A10: P008 | B10: Ball Pen Box (10pcs) | C10: Stationery | D10: 55 | E10: 90 | F10: S105
A11: P009 | B11: Biscuit Pack 250g | C11: Snacks | D11: 30 | E11: 50 | F11: S106
A12: P010 | B12: Chips 150g | C12: Snacks | D12: 25 | E12: 45 | F12: S106
A13: P011 | B13: Green Tea 50 bags | C13: Beverages | D13: 120 | E13: 180 | F13: S107
A14: P012 | B14: Instant Coffee 100g | C14: Beverages | D14: 210 | E14: 295 | F14: S107
E17: Name | F17: Toor dal 1kg
E18: Selling Price | F18: =INDEX(E2:E14,MATCH(F17,B2:B14,0)) -> 155
B24: INDEX | C24: =INDEX(E3:E14,4) -> 240
B25: MATCH | C25: =MATCH("INSTANT COFFEE 100G",B3:B14,) -> 12
B26: INDEX AND MATCH | C26: =INDEX(E3:E14,MATCH("GREEN TEA 50 BAGS",B3:B14,)) -> 180

Sheet Supplier_Master
A1: ZenithMart Pvt. Ltd. — Supplier Master Table
A2: Supplier_ID | B2: Supplier_Name | C2: Region | D2: Lead_Time (days) | E2: Discount (%)
A3: S101 | B3: AgroFresh Traders | C3: South India | D3: 5 | E3: 8
A4: S102 | B4: SunDrop Oils Ltd. | C4: West India | D4: 7 | E4: 5
A5: S103 | B5: Kerala Naturals | C5: South India | D5: 4 | E5: 10
A6: S104 | B6: FMCG Distributors | C6: Pan India | D6: 3 | E6: 6
A7: S105 | B7: OfficeLine Supplies | C7: North India | D7: 6 | E7: 4
A8: S106 | B8: SnackWave Co. | C8: West India | D8: 2 | E8: 7
A9: S107 | B9: BevCraft India | C9: East India | D9: 5 | E9: 9
C14: =INDEX(A3:E9, 5,4) -> 6 | D14: =_xlfn.FORMULATEXT(C14) -> =INDEX(A3:E9, 5,4)
C16: =MATCH("FMCG Distributors", B3:B9, 0) -> 4 | D16: =_xlfn.FORMULATEXT(C16) -> =MATCH("FMCG Distributors", B3:B9, 0)
C18: =INDEX(E3:E9,MATCH("OfficeLine Supplies",B3:B9,0)) -> 4 | D18: =_xlfn.FORMULATEXT(C18) -> =INDEX(E3:E9,MATCH("OfficeLine Supplies",B3:B9,0))

Sheet Sales_Transactions
A1: ZenithMart Pvt. Ltd. — Monthly Sales Transactions (April 2025)
A2: Transaction_ID | B2: Date | C2: Product_ID | D2: Store_ID | E2: Qty_Sold | F2: Unit_Price (₹) | G2: Discount_Applied (%) | H2: Net_Revenue (₹)
A3: T001 | B3: 01-Apr-25 | C3: P001 | D3: ST01 | E3: 50 | F3: 310 | G3: 5 | H3: =E3*F3*(1-G3/100) -> 14725
A4: T002 | B4: 01-Apr-25 | C4: P003 | D4: ST02 | E4: 30 | F4: 195 | G4: 0 | H4: =E4*F4*(1-G4/100) -> 5850
A5: T003 | B5: 02-Apr-25 | C5: P005 | D5: ST01 | E5: 80 | F5: 95 | G5: 10 | H5: =E5*F5*(1-G5/100) -> 6840
A6: T004 | B6: 02-Apr-25 | C6: P009 | D6: ST03 | E6: 120 | F6: 50 | G6: 0 | H6: =E6*F6*(1-G6/100) -> 6000
A7: T005 | B7: 03-Apr-25 | C7: P002 | D7: ST02 | E7: 60 | F7: 155 | G7: 5 | H7: =E7*F7*(1-G7/100) -> 8835
A8: T006 | B8: 03-Apr-25 | C8: P011 | D8: ST01 | E8: 40 | F8: 180 | G8: 8 | H8: =E8*F8*(1-G8/100) -> 6624
A9: T007 | B9: 04-Apr-25 | C9: P007 | D9: ST03 | E9: 25 | F9: 70 | G9: 0 | H9: =E9*F9*(1-G9/100) -> 1750
A10: T008 | B10: 04-Apr-25 | C10: P004 | D10: ST02 | E10: 35 | F10: 240 | G10: 10 | H10: =E10*F10*(1-G10/100) -> 7560
A11: T009 | B11: 05-Apr-25 | C11: P012 | D11: ST01 | E11: 20 | F11: 295 | G11: 5 | H11: =E11*F11*(1-G11/100) -> 5605
A12: T010 | B12: 05-Apr-25 | C12: P006 | D12: ST03 | E12: 90 | F12: 75 | G12: 0 | H12: =E12*F12*(1-G12/100) -> 6750
A13: T011 | B13: 06-Apr-25 | C13: P010 | D13: ST02 | E13: 150 | F13: 45 | G13: 0 | H13: =E13*F13*(1-G13/100) -> 6750
A14: T012 | B14: 06-Apr-25 | C14: P008 | D14: ST01 | E14: 45 | F14: 90 | G14: 5 | H14: =E14*F14*(1-G14/100) -> 3847.5
... A22: T020 | B22: 10-Apr-25 | C22: P012 | D22: ST01 | E22: 15 | F22: 295 | G22: 5 | H22: =E22*F22*(1-G22/100) -> 4203.75

Sheet Inventory_Status
A1: ZenithMart Pvt. Ltd. — Inventory Status (End of March 2025)
A2: Product_ID | B2: Stock_Available | C2: Reorder_Level | D2: Stock_Status | E2: Warehouse_Location | F2: Last_Restocked | G2: Days_to_Expiry
A3: P001 | B3: 80 | C3: 50 | D3: Adequate | E3: WH-A1 | F3: 15-Mar-25 | G3: 180
A4: P002 | B4: 30 | C4: 40 | D4: Low | E4: WH-A2 | F4: 10-Mar-25 | G4: 365
A5: P003 | B5: 120 | C5: 60 | D5: Adequate | E5: WH-B1 | F5: 20-Mar-25 | G5: 270
A6: P004 | B6: 25 | C6: 30 | D6: Low | E6: WH-B2 | F6: 05-Mar-25 | G6: 365
A7: P005 | B7: 200 | C7: 80 | D7: Adequate | E7: WH-C1 | F7: 22-Mar-25 | G7: 730
A8: P006 | B8: 150 | C8: 70 | D8: Adequate | E8: WH-C1 | F8: 22-Mar-25 | G8: 365
A9: P007 | B9: 60 | C9: 50 | D9: Adequate | E9: WH-D1 | F9: 18-Mar-25 | G9: 1095
A10: P008 | B10: 15 | C10: 25 | D10: Critical | E10: WH-D1 | F10: 01-Mar-25 | G10: 1095
A11: P009 | B11: 300 | C11: 100 | D11: Adequate | E11: WH-E1 | F11: 25-Mar-25 | G11: 90
A12: P010 | B12: 400 | C12: 120 | D12: Adequate | E12: WH-E2 | F12: 25-Mar-25 | G12: 120
A13: P011 | B13: 45 | C13: 40 | D13: Adequate | E13: WH-F1 | F13: 12-Mar-25 | G13: 730
A14: P012 | B14: 10 | C14: 20 | D14: Critical | E14: WH-F1 | F14: 08-Mar-25 | G14: 365

Sheet Lookup_Practice
A1: ZenithMart — Lookup Function Practice Worksheet (Complete the Yellow Cells)
A3: SECTION A — VLOOKUP: Retrieve Product Details from Product_Master
A4: Product_ID | B4: Product_Name | C4: Category | D4: Unit_Cost (₹) | E4: Selling_Price (₹) | F4: Supplier_ID
A5: P003 | B5: =VLOOKUP(A5, Product_Master!A3:F14, 2, TRUE) -> Sunflower Oil 1L | C5: =VLOOKUP(A5, Product_Master!A3:F14, 3, TRUE) -> Edible Oils | D5: =VLOOKUP(A5, Product_Master!A3:F14, 4, TRUE) -> 145 | E5: =VLOOKUP(A5, Product_Master!A3:F14, 5, TRUE) -> 195 | F5: =VLOOKUP(A5, Product_Master!A3:F14, 6, TRUE) -> S102
A6: P007 | B6: =VLOOKUP(A6, Product_Master!A4:F15, 2, TRUE) -> Notebook 200 pages | C6: =VLOOKUP(A6, Product_Master!A4:F15, 3, TRUE) -> Stationery | D6: =VLOOKUP(A6, Product_Master!A4:F15, 4, TRUE) -> 40 | E6: =VLOOKUP(A6, Product_Master!A4:F15, 5, TRUE) -> 70 | F6: =VLOOKUP(A6, Product_Master!A4:F15, 6, TRUE) -> S105
A7: P010 | B7: =VLOOKUP(A7, Product_Master!A5:F16, 2, TRUE) -> Chips 150g | C7: =VLOOKUP(A7, Product_Master!A5:F16, 3, TRUE) -> Snacks | D7: =VLOOKUP(A7, Product_Master!A5:F16, 4, TRUE) -> 25 | E7: =VLOOKUP(A7, Product_Master!A5:F16, 5, TRUE) -> 45 | F7: =VLOOKUP(A7, Product_Master!A5:F16, 6, TRUE) -> S106
A8: P012 | B8: =VLOOKUP(A8, Product_Master!A6:F17, 2, TRUE) -> Instant Coffee 100g | C8: =VLOOKUP(A8, Product_Master!A6:F17, 3, TRUE) -> Beverages | D8: =VLOOKUP(A8, Product_Master!A6:F17, 4, TRUE) -> 210 | E8: =VLOOKUP(A8, Product_Master!A6:F17, 5, TRUE) -> 295 | F8: =VLOOKUP(A8, Product_Master!A6:F17, 6, TRUE) -> S107
A10: 💡 Syntax: =VLOOKUP(lookup_value, table_array, col_index_num, [range_lookup])
A12: SECTION B — INDEX-MATCH: Find Supplier Name & Lead Time for a Given Product
A13: Product_ID | B13: Supplier_ID | C13: Supplier_Name | D13: Region | E13: Lead_Time (days) | F13: Discount (%)
A14: P001 | B14: =VLOOKUP(A14, Product_Master!A3:F14, 6, TRUE) -> S101 | C14: =INDEX(Supplier_Master!B3:B9, MATCH(B14, Supplier_Master!A3:A9, 0)) -> AgroFresh Traders | D14: =INDEX(Supplier_Master!C3:C9, MATCH(B14, Supplier_Master!A3:A9, 0)) -> South India | E14: =INDEX(Supplier_Master!D3:D9, MATCH(B14, Supplier_Master!A3:A9, 0)) -> 5 | F14: =INDEX(Supplier_Master!E3:E9, MATCH(C14, Supplier_Master!B3:B9, 0)) -> 8
A15: P004 | B15: =VLOOKUP(A15, Product_Master!A4:F15, 6, TRUE) -> S103 | C15: =INDEX(Supplier_Master!B4:B10, MATCH(B15, Supplier_Master!A4:A10, 0)) -> Kerala Naturals | D15: =INDEX(Supplier_Master!C3:C9, MATCH(B15, Supplier_Master!A3:A9, 0)) -> South India | E15: =INDEX(Supplier_Master!D3:D9, MATCH(B15, Supplier_Master!A3:A9, 0)) -> 4 | F15: =INDEX(Supplier_Master!E3:E9, MATCH(C15, Supplier_Master!B3:B9, 0)) -> 10
A16: P008 | B16: =VLOOKUP(A16, Product_Master!A5:F16, 6, TRUE) -> S105 | C16: =INDEX(Supplier_Master!B5:B11, MATCH(B16, Supplier_Master!A5:A11, 0)) -> OfficeLine Supplies | D16: =INDEX(Supplier_Master!C3:C9, MATCH(B16, Supplier_Master!A3:A9, 0)) -> North India | E16: =INDEX(Supplier_Master!D3:D9, MATCH(B16, Supplier_Master!A3:A9, 0)) -> 6 | F16: =INDEX(Supplier_Master!E3:E9, MATCH(C16, Supplier_Master!B3:B9, 0)) -> 4
A17: P011 | B17: =VLOOKUP(A17, Product_Master!A6:F17, 6, TRUE) -> S107 | C17: =INDEX(Supplier_Master!B6:B12, MATCH(B17, Supplier_Master!A6:A12, 0)) -> BevCraft India | D17: =INDEX(Supplier_Master!C3:C9, MATCH(B17, Supplier_Master!A3:A9, 0)) -> East India | E17: =INDEX(Supplier_Master!D3:D9, MATCH(B17, Supplier_Master!A3:A9, 0)) -> 5 | F17: =INDEX(Supplier_Master!E3:E9, MATCH(C17, Supplier_Master!B3:B9, 0)) -> 9
A19: 💡 Syntax: =INDEX(return_range, MATCH(lookup_value, lookup_range, 0))
A21: SECTION C — XLOOKUP: Retrieve Inventory Status & Location
A22: Product_ID | B22: Product_Name | C22: Stock_Available | D22: Reorder_Level | E22: Stock_Status | F22: Warehouse_Location
A23: P002 | B23: =_xlfn.XLOOKUP(A23, Product_Master!A3:A14, Product_Master!B3:B14, "not found",0) -> Toor Dal 1kg | C23: =_xlfn.XLOOKUP(A23, Inventory_Status!A3:A14, Inventory_Status!B3:B14, "not found",0) -> 30 | D23: =_xlfn.XLOOKUP(A23, Inventory_Status!A3:A14, Inventory_Status!C3:C14, "not found",0) -> 40 | E23: =_xlfn.XLOOKUP(A23, Inventory_Status!A3:A14, Inventory_Status!D3:D14, "not found",0) -> Low | F23: =_xlfn.XLOOKUP(A23, Inventory_Status!A3:A14, Inventory_Status!E3:E14, "not found",0) -> WH-A2
A24: P006 | B24: =_xlfn.XLOOKUP(A24, Product_Master!A3:A14, Product_Master!B3:B14, "not found",0) -> Dove Soap 100g | C24: =_xlfn.XLOOKUP(A24, Inventory_Status!A3:A14, Inventory_Status!B3:B14, "not found",0) -> 150 | D24: =_xlfn.XLOOKUP(A24, Inventory_Status!A3:A14, Inventory_Status!C3:C14, "not found",0) -> 70 | E24: =_xlfn.XLOOKUP(A24, Inventory_Status!A3:A14, Inventory_Status!D3:D14, "not found",0) -> Adequate | F24: =_xlfn.XLOOKUP(A24, Inventory_Status!A3:A14, Inventory_Status!E3:E14, "not found",0) -> WH-C1
A25: P008 | B25: =_xlfn.XLOOKUP(A25, Product_Master!A3:A14, Product_Master!B3:B14, "not found",0) -> Ball Pen Box (10pcs) | C25: =_xlfn.XLOOKUP(A25, Inventory_Status!A3:A14, Inventory_Status!B3:B14, "not found",0) -> 15 | D25: =_xlfn.XLOOKUP(A25, Inventory_Status!A3:A14, Inventory_Status!C3:C14, "not found",0) -> 25 | E25: =_xlfn.XLOOKUP(A25, Inventory_Status!A3:A14, Inventory_Status!D3:D14, "not found",0) -> Critical | F25: =_xlfn.XLOOKUP(A25, Inventory_Status!A3:A14, Inventory_Status!E3:E14, "not found",0) -> WH-D1
A26: P012 | B26: =_xlfn.XLOOKUP(A26, Product_Master!A3:A14, Product_Master!B3:B14, "not found",0) -> Instant Coffee 100g | C26: =_xlfn.XLOOKUP(A26, Inventory_Status!A3:A14, Inventory_Status!B3:B14, "not found",0) -> 10 | D26: =_xlfn.XLOOKUP(A26, Inventory_Status!A3:A14, Inventory_Status!C3:C14, "not found",0) -> 20 | E26: =_xlfn.XLOOKUP(A26, Inventory_Status!A3:A14, Inventory_Status!D3:D14, "not found",0) -> Critical | F26: =_xlfn.XLOOKUP(A26, Inventory_Status!A3:A14, Inventory_Status!E3:E14, "not found",0) -> WH-F1
A28: 💡 XLOOKUP Syntax: =XLOOKUP(lookup_value, lookup_array, return_array, [if_not_found]) | Shown here as INDEX-MATCH for compatibility; use XLOOKUP in Microsoft 365 / Excel 2021+
A30: SECTION D — Combined Lookup: Enrich Sales Transactions with Product & Supplier Info
A31: Transaction_ID | B31: Product_ID | C31: Product_Name | D31: Category | E31: Supplier_Name | F31: Net_Revenue (₹) | G31: Stock_Status
A32: T001 | B32: =_xlfn.XLOOKUP(A32, Sales_Transactions!A3:A22, Sales_Transactions!C3:C22, "not found",0) -> P001 | C32: =_xlfn.XLOOKUP(B32, Product_Master!A3:A14, Product_Master!B3:B14, "not found",0) -> Basmati Rice 5kg | D32: =_xlfn.XLOOKUP(B32, Product_Master!A3:A14, Product_Master!C3:C14, "not found",0) -> Staples | E32: =_xlfn.XLOOKUP(_xlfn.XLOOKUP(B32, Product_Master!A:A, Product_Master!F:F, "not found", 0),Supplier_Master!A:A,Supplier_Master!B:B,"not found",0) -> AgroFresh Traders | F32: =_xlfn.XLOOKUP(A32, Sales_Transactions!A3:A22, Sales_Transactions!H3:H22, "not found",0) -> 14725 | G32: =_xlfn.XLOOKUP(B32, Inventory_Status!A3:A14, Inventory_Status!D3:D14, "not found",0) -> Adequate
A33: T004 | B33: =_xlfn.XLOOKUP(A33, Sales_Transactions!A3:A22, Sales_Transactions!C3:C22, "not found",0) -> P009 | C33: =_xlfn.XLOOKUP(B33, Product_Master!A3:A14, Product_Master!B3:B14, "not found",0) -> Biscuit Pack 250g | D33: =_xlfn.XLOOKUP(B33, Product_Master!A3:A14, Product_Master!C3:C14, "not found",0) -> Snacks | E33: =_xlfn.XLOOKUP(_xlfn.XLOOKUP(B33, Product_Master!A:A, Product_Master!F:F, "not found", 0),Supplier_Master!A:A,Supplier_Master!B:B,"not found",0) -> SnackWave Co. | F33: =_xlfn.XLOOKUP(A33, Sales_Transactions!A3:A22, Sales_Transactions!H3:H22, "not found",0) -> 6000 | G33: =_xlfn.XLOOKUP(B33, Inventory_Status!A3:A14, Inventory_Status!D3:D14, "not found",0) -> Adequate
A34: T008 | B34: =_xlfn.XLOOKUP(A34, Sales_Transactions!A3:A22, Sales_Transactions!C3:C22, "not found",0) -> P004 | C34: =_xlfn.XLOOKUP(B34, Product_Master!A3:A14, Product_Master!B3:B14, "not found",0) -> Coconut Oil 500ml | D34: =_xlfn.XLOOKUP(B34, Product_Master!A3:A14, Product_Master!C3:C14, "not found",0) -> Edible Oils | E34: =_xlfn.XLOOKUP(_xlfn.XLOOKUP(B34, Product_Master!A:A, Product_Master!F:F, "not found", 0),Supplier_Master!A:A,Supplier_Master!B:B,"not found",0) -> Kerala Naturals | F34: =_xlfn.XLOOKUP(A34, Sales_Transactions!A3:A22, Sales_Transactions!H3:H22, "not found",0) -> 7560 | G34: =_xlfn.XLOOKUP(B34, Inventory_Status!A3:A14, Inventory_Status!D3:D14, "not found",0) -> Low
A35: T012 | B35: =_xlfn.XLOOKUP(A35, Sales_Transactions!A3:A22, Sales_Transactions!C3:C22, "not found",0) -> P008 | C35: =_xlfn.XLOOKUP(B35, Product_Master!A3:A14, Product_Master!B3:B14, "not found",0) -> Ball Pen Box (10pcs) | D35: =_xlfn.XLOOKUP(B35, Product_Master!A3:A14, Product_Master!C3:C14, "not found",0) -> Stationery | E35: =_xlfn.XLOOKUP(_xlfn.XLOOKUP(B35, Product_Master!A:A, Product_Master!F:F, "not found", 0),Supplier_Master!A:A,Supplier_Master!B:B,"not found",0) -> OfficeLine Supplies | F35: =_xlfn.XLOOKUP(A35, Sales_Transactions!A3:A22, Sales_Transactions!H3:H22, "not found",0) -> 3847.5 | G35: =_xlfn.XLOOKUP(B35, Inventory_Status!A3:A14, Inventory_Status!D3:D14, "not found",0) -> Critical
A36: T020 | B36: =_xlfn.XLOOKUP(A36, Sales_Transactions!A3:A22, Sales_Transactions!C3:C22, "not found",0) -> P012 | C36: =_xlfn.XLOOKUP(B36, Product_Master!A3:A14, Product_Master!B3:B14, "not found",0) -> Instant Coffee 100g | D36: =_xlfn.XLOOKUP(B36, Product_Master!A3:A14, Product_Master!C3:C14, "not found",0) -> Beverages | E36: =_xlfn.XLOOKUP(_xlfn.XLOOKUP(B36, Product_Master!A:A, Product_Master!F:F, "not found", 0),Supplier_Master!A:A,Supplier_Master!B:B,"not found",0) -> BevCraft India | F36: =_xlfn.XLOOKUP(A36, Sales_Transactions!A3:A22, Sales_Transactions!H3:H22, "not found",0) -> 4203.75 | G36: =_xlfn.XLOOKUP(B36, Inventory_Status!A3:A14, Inventory_Status!D3:D14, "not found",0) -> Critical
