Workbook

Sheet Dashboard
A1: AKASA AIR – FINANCIAL FORECAST DASHBOARD (FY 2026-27 to FY 2028-29)
A2: SNV Aviation Private Limited | Figures in INR Crores | All forecasts are projections, not guarantees
A3: AI PROMPT USED IN THIS MODEL
A4: You are senior financial analyst specializing in the Indian aviation industry. I am an MBA student preparing a financial forecasting assignment. Using the historical financial statements and supporting data provided below for Akasa Air (SNV Aviation Private Limited), prepare a three-year financial forecast for FY 2026–27, FY 2027–28, and FY 2028–29 in Microsoft Excel. The workbook should contain the following worksheets: 1. Dashboard (summary metrics, charts, AI disclosure); 2. Assumptions (revenue growth, traffic, load factor, yield, fleet, fuel, employee, maintenance, airport charges, lease rentals, D&A, finance costs, tax, working capital); 3. Profit & Loss Statement (Revenue → EBITDAR → EBIT → EBT → PAT); 4. Balance Sheet (Current/Non-current Assets, ROU Assets, Cash, Lease Liabilities, Equity, Accumulated Deficit); 5. Cash Flow Statement – Indirect Method (CFO, CFI, CFF, Opening/Closing Cash). Requirements: Fully integrated three-statement model with Excel formulas; projections based on historical trends and Indian aviation industry assumptions; document every assumption; ensure Balance Sheet balances; professional MBA-grade Excel formatting; if historical data unavailable, state assumptions explicitly. On the first sheet, add the AI prompt used.
A10: KEY FINANCIAL METRICS SUMMARY
A11: Metric | B11: FY 2022-23 (Partial/Est.) | C11: FY 2023-24 (Approx.) | D11: FY 2024-25 (Prelim.) | E11: FY 2026-27 (Forecast) | F11: FY 2027-28 (Forecast) | G11: FY 2028-29 (Forecast)
A12: Revenue (INR Cr) | B12: ='P&L Statement'!B6 -> 850 | C12: ='P&L Statement'!C6 -> 4580 | D12: ='P&L Statement'!D6 -> 8350 | E12: ='P&L Statement'!E6 -> 11690 | F12: ='P&L Statement'!F6 -> 15430.8 | G12: ='P&L Statement'!G6 -> 19288.5
A13: Revenue Growth (%) | B13: — | C13: =('P&L Statement'!C6-'P&L Statement'!B6)/'P&L Statement'!B6 -> 4.3882353 | D13: =('P&L Statement'!D6-'P&L Statement'!C6)/'P&L Statement'!C6 -> 0.8231441 | E13: =Assumptions!B10 -> 0.4 | F13: =Assumptions!C10 -> 0.32 | G13: =Assumptions!D10 -> 0.25
A14: EBITDAR (INR Cr) | B14: ='P&L Statement'!B16 -> -530 | C14: ='P&L Statement'!C16 -> -1250 | D14: ='P&L Statement'!D16 -> -1100 | E14: ='P&L Statement'!E16 -> 2045.75 | F14: ='P&L Statement'!F16 -> 2885.5596 | G14: ='P&L Statement'!G16 -> 3838.4115
A15: EBITDAR Margin (%) | B15: ='P&L Statement'!B17 -> -0.62352941 | C15: ='P&L Statement'!C17 -> -0.27292576 | D15: ='P&L Statement'!D17 -> -0.13173653 | E15: ='P&L Statement'!E17 -> 0.175 | F15: ='P&L Statement'!F17 -> 0.187 | G15: ='P&L Statement'!G17 -> 0.199
A16: PAT (INR Cr) | B16: ='P&L Statement'!B26 -> -875 | C16: ='P&L Statement'!C26 -> -2250 | D16: ='P&L Statement'!D26 -> -2880 | E16: ='P&L Statement'!E26 -> -1928.85 | F16: ='P&L Statement'!F26 -> -2175.7428 | G16: ='P&L Statement'!G26 -> -2237.466
A17: PAT Margin (%) | B17: ='P&L Statement'!B27 -> -1.0294118 | C17: ='P&L Statement'!C27 -> -0.49126638 | D17: ='P&L Statement'!D27 -> -0.34491018 | E17: ='P&L Statement'!E27 -> -0.165 | F17: ='P&L Statement'!F27 -> -0.141 | G17: ='P&L Statement'!G27 -> -0.116
A18: Fleet Size (aircraft) | B18: 12 | C18: 55 | D18: 88 | E18: =Assumptions!B5 -> 130 | F18: =Assumptions!C5 -> 170 | G18: =Assumptions!D5 -> 210
A19: Passengers (million) | B19: 2.1 | C19: 12.4 | D19: 21.5 | E19: =Assumptions!B6 -> 32 | F19: =Assumptions!C6 -> 42 | G19: =Assumptions!D6 -> 54
A20: Load Factor (%) | B20: 0.82 | C20: 0.855 | D20: 0.87 | E20: =Assumptions!B7 -> 0.87 | F20: =Assumptions!C7 -> 0.875 | G20: =Assumptions!D7 -> 0.88
A21: Cash Balance (INR Cr) | B21: ='Balance Sheet'!B7 -> 4200 | C21: ='Balance Sheet'!C7 -> 3100 | D21: ='Balance Sheet'!D7 -> 2400 | E21: ='Balance Sheet'!E7 -> 4535.0015 | F21: ='Balance Sheet'!F7 -> 5456.5245 | G21: ='Balance Sheet'!G7 -> 6022.967
A23: AI DISCLOSURE NOTE
A24: This financial forecast model for Akasa Air was prepared with AI assistance (Claude by Anthropic, claude.ai) for academic purposes. The following components were AI-generated or AI-assisted: 1. MODEL STRUCTURE & FORMULAS: The entire three-statement integrated model (P&L, Balance Sheet, Cash Flow) was structured and all Excel formulas were written by AI. 2. ASSUMPTIONS: All forecasting assumptions (revenue growth rates, cost ratios, working capital days, fleet expansion, ROU asset calculations) were formulated by AI based on publicly available information about Akasa Air and the Indian aviation industry. 3. HISTORICAL DATA: ⚠ NO HISTORICAL FINANCIAL STATEMENTS WERE PROVIDED BY THE USER. All historical figures (FY23–FY25) are approximate estimates compiled by AI from public domain sources including MCA filings, DGCA monthly reports, and press coverage. These figures have NOT been audited or independently verified. Users MUST replace all historical data with verified figures from SNV Aviation Pvt Ltd's official ROC filings / MCA portal before submitting this assignment. 4. RATIONALE: The industry context, rationale for assumptions, and risk factors were authored by AI. AI Tool: Claude (Anthropic) | Model: Claude Sonnet 4.6 | Date: June 2026 All forecasts are forward-looking estimates; actual results may differ materially. This does not constitute investment advice. Final accuracy responsibility rests with the student.
A34: DATA SOURCE & DISCLAIMER
A35: Historical data sources (all approximate – MUST be verified): • Revenue / P&L: MCA ROC filing for SNV Aviation Pvt Ltd (Company CIN to be verified from MCA21 portal) • Fleet data: DGCA Monthly Statistics (dgca.gov.in) – monthly fleet/traffic reports • Passenger data: DGCA – Domestic Air Traffic Statistics • Industry benchmarks: IATA, CAPA Centre for Aviation, IndiGo & Air India annual reports for comp. ratios • Lease & ROU data: Ind AS 116 disclosures from airline peers (IndiGo DRHP/Annual Reports) KEY RISKS TO FORECAST: (1) Boeing 737 MAX delivery delays; (2) ATF price volatility; (3) Competition from IndiGo, Air India, SpiceJet; (4) Regulatory changes (DGCA/AERA/MoCA); (5) Rupee depreciation (lease payments in USD); (6) Pilot shortage / wage inflation.
A42: COLOUR CODING GUIDE
A43: Blue text = Hardcoded input cells (user-editable assumptions)
A44: Black text = Formula cells (calculated)
A45: Dark green text = Cross-sheet links (referencing another tab)
A46: Orange highlight = Key risk / AI-estimated figure needing verification
A47: Navy background = Grand total / key header rows
A48: Teal background = Section headers
A49: Light blue background = Subtotals

Sheet Assumptions
A1: AKASA AIR (SNV AVIATION PVT LTD) – FORECAST ASSUMPTIONS
A2: ⚠ DATA WARNING: No financial statements were provided. All historical figures are approximate estimates from MCA filings, DGCA reports, and press sources. Verify against official SNV Aviation Pvt Ltd ROC filings before submission.
A3: Assumption | B3: FY 2026-27 | C3: FY 2027-28 | D3: FY 2028-29 | E3: Rationale / Source
A4: A. FLEET & PASSENGER TRAFFIC
A5: Fleet Size (end of year – aircraft) | B5: 130 | C5: 170 | D5: 210 | E5: Akasa had ~88 aircraft by end FY25 (approx). Management has indicated an order book of 226 Boeing 737 MAX aircraft with deliveries through FY2031. Assuming ~40 deliveries per year (net of any returns/sub-leases). Verify against Boeing delivery schedules and DGCA fleet data.
A6: Passengers Carried (million) | B6: 32 | C6: 42 | D6: 54 | E6: DGCA data: Akasa carried ~21.5 mn passengers in FY25 (est). Fleet growth drives seat capacity growth. Assuming ~49–50% growth in FY27 as new aircraft ramp up, moderating to ~31% and ~29% as fleet matures. I'm not certain of exact DGCA figures; verify from DGCA monthly data.
A7: Average Load Factor (%) | B7: 0.87 | C7: 0.875 | D7: 0.88 | E7: Industry average LF in India ~87–89% (IndiGo ~87%, Air India ~83%). Akasa reported ~86–88% LF in FY25 per press reports. Assume gradual improvement as network matures. Source: DGCA Monthly Capacity/Traffic Statistics.
A8: Average Yield (INR per passenger) | B8: 3900 | C8: 4050 | D8: 4200 | E8: Blended yield estimated from revenue ÷ passengers. FY25 est: 8350/21.5 ≈ ₹3,880. Modest yield improvement of ~3–4% p.a. from network mix and ancillary revenue growth. Indian aviation yield growth constrained by competition; conservative assumption.
A9: B. REVENUE
A10: Revenue Growth Rate (%) | B10: 0.4 | C10: 0.32 | D10: 0.25 | E10: Derived from fleet and passenger growth. FY27: +40% (fleet ramp from 88→130). FY28: +32% (fleet 130→170). FY29: +25% (fleet 170→210). Consistent with Indian aviation growth trajectory for a scaling LCC. Note: No FY26 transition year is modelled due to data gap.
A11: Ancillary Revenue (% of total revenue) | B11: 0.08 | C11: 0.09 | D11: 0.1 | E11: Baggage fees, seat upgrades, cargo, in-flight sales. Industry peers (IndiGo) generate ~8–12% ancillary. Akasa growing this stream. Gradual increase as product mix broadens.
A12: C. OPERATING COSTS
A13: Fuel Cost (% of Revenue) | B13: 0.425 | C13: 0.42 | D13: 0.415 | E13: ATF (aviation turbine fuel) is the largest cost item for Indian airlines. FY25 est: ~56% of opex or ~43% of revenue. Fuel efficiency improving as Boeing 737 MAX is ~14% more fuel-efficient than older-generation aircraft. ATF price assumed broadly stable at ~₹90–95/litre. Verify from IOCL ATF pricing.
A14: Employee Cost (% of Revenue) | B14: 0.115 | C14: 0.11 | D14: 0.105 | E14: FY25 est ~12–13% of revenue. Scale benefits reduce per-seat employee cost as headcount grows slower than fleet. Pilot hiring remains a bottleneck; assume wage inflation ~8% p.a. offset by productivity improvements.
A15: Maintenance & Engineering (% of Revenue) | B15: 0.08 | C15: 0.082 | D15: 0.085 | E15: FY25 est ~9.3% of revenue. Slight increase as fleet ages and PDR cycles kick in. 737 MAX has lower maintenance burden than previous-gen aircraft initially. Power-by-the-hour contracts with CFM assumed for engines.
A16: Airport & Navigation Charges (% of Revenue) | B16: 0.11 | C16: 0.108 | D16: 0.106 | E16: Includes landing fees, CUTE charges, ATC/navigation charges, ground handling. AERA airport tariff revisions create upward pressure. Slight efficiency gain from higher utilisation per aircraft.
A17: Aircraft Lease Rentals (% of Revenue) – EBITDAR add-back | B17: 0.155 | C17: 0.15 | D17: 0.145 | E17: Operating lease rentals for Boeing 737 MAX aircraft. Typical rate ~USD 350–420k/month per aircraft for new narrow-body. Decreasing as % of revenue due to revenue growth outpacing fleet additions. IMPORTANT: These are ABOVE the EBITDAR line (added back for EBITDAR calculation).
A18: Other Operating Expenses (% of Revenue) | B18: 0.095 | C18: 0.093 | D18: 0.09 | E18: Distribution/GDS, CASS, passenger meals (Akasa is hybrid model), insurance, navigation aids, uniforms, other. Modest scale benefits assumed.
A19: D. DEPRECIATION & AMORTISATION
A20: D&A (% of Revenue) – incl. ROU amortisation | B20: 0.095 | C20: 0.093 | D20: 0.09 | E20: Includes: (1) ROU amortisation on aircraft leases under Ind AS 116; (2) PPE depreciation (simulators, IT, furniture). FY25 est: ~11% of revenue. Declining % as revenue grows faster than fleet adds. ROU amortisation is the dominant item.
A21: E. FINANCE COSTS
A22: Finance Costs (% of Revenue) – incl. lease interest | B22: 0.09 | C22: 0.085 | D22: 0.08 | E22: Includes: (1) Interest on lease liabilities (Ind AS 116); (2) interest on working capital / other borrowings. FY25 est ~10.3% of revenue. Declining as revenue scales and lease liabilities mature. Rate implied ~8–9% on lease liabilities.
A23: F. TAXATION
A24: Effective Tax Rate (%) | B24: 0 | C24: 0 | D24: 0 | E24: Akasa is loss-making (FY23–FY25). Deferred tax assets recognised only if future taxable profits are virtually certain. Assuming NIL tax through forecast period as carried-forward losses (₹6,000+ Cr accumulated deficit) offset any profit. This is a key uncertainty – if Akasa turns profitable in FY29, MAT (15%) may apply.
A25: G. WORKING CAPITAL
A26: Receivable Days | B26: 15 | C26: 14 | D26: 13 | E26: Airlines are predominantly cash/prepaid businesses. Receivables arise from corporate travel agencies, cargo, codeshare partners. Low debtor days typical.
A27: Creditor / Payable Days | B27: 38 | C27: 40 | D27: 42 | E27: Payments to IOCL (fuel), airport operators (AAI), handlers. Gradual improvement in payable terms as Akasa's scale improves bargaining position.
A28: Other Current Assets (% of Revenue) | B28: 0.075 | C28: 0.073 | D28: 0.07 | E28: Advances to vendors, deposits, prepaid expenses, deferred charges. Declining as % of revenue with scale.
A29: Other Current Liabilities (% of Revenue) | B29: 0.12 | C29: 0.118 | D29: 0.115 | E29: Advance ticket sales (deferred revenue), statutory dues, accrued expenses, security deposits from agents. High for airlines due to advance ticket sales.
A30: H. CAPEX & BALANCE SHEET ASSUMPTIONS
A31: Capex – PPE additions (INR Cr) | B31: 420 | C31: 550 | D31: 680 | E31: Flight simulators, IT infrastructure, cabin crew training facilities, station equipment. Does NOT include aircraft (handled as leases under Ind AS 116). Growing with fleet expansion.
A32: New ROU Asset additions per aircraft (INR Cr/aircraft) | B32: 24 | C32: 25 | D32: 26 | E32: Each new Boeing 737 MAX lease generates an ROU asset = PV of lease payments. Typical: USD 350k/month × 12 yrs discounted at 8% ≈ USD 31mn ≈ ~₹26Cr at 84 USD/INR. Slight increase as newer delivery slots cost more.
A33: New Aircraft Delivered (net of exits) | B33: 42 | C33: 40 | D33: 40 | E33: Derived from fleet size change YoY. FY27: 130-88=42 net adds. Assumes Boeing 737 MAX deliveries per contracted schedule. Note: Boeing production delays are a key risk – verify current slot allocations.
A34: New Equity Raised (INR Cr) | B34: 2500 | C34: 2000 | D34: 1500 | E34: Akasa backed by Rakesh Jhunjhunwala family and institutional investors. Company expected to need additional capital to fund growth and cover losses. Assumed equity infusion annually. THIS IS A KEY ASSUMPTION – actual funding rounds may differ significantly.
A35: Implied Interest Rate on Lease Liabilities (%) | B35: 0.085 | C35: 0.085 | D35: 0.085 | E35: Incremental borrowing rate used to discount lease liabilities under Ind AS 116. Assumed at 8.5% p.a., consistent with Indian corporate borrowing rates for investment-grade (or near-IG) airline credits.
A37: COLOUR KEY: Blue = Hardcoded input (editable) | Black = Formula | Dark Green = Cross-sheet link | Orange = Warning / AI-disclosed assumption

Sheet P&L Statement
A1: AKASA AIR (SNV AVIATION PVT LTD) – PROJECTED PROFIT & LOSS STATEMENT (INR Crores)
A2: ⚠ Historical figures are approximate estimates (MCA/DGCA/press). FY26 transition year not modelled. Forecast starts FY27. Verify all historical data.
A3: Particulars (INR Crores) | B3: FY 2022-23 (Partial/Est.) | C3: FY 2023-24 (Approx.) | D3: FY 2024-25 (Prelim.) | E3: FY 2026-27 (Forecast) | F3: FY 2027-28 (Forecast) | G3: FY 2028-29 (Forecast)
B4: ◄ HISTORICAL (Approximate) ► | E4: ◄ FORECAST ►
A5: I. REVENUE
A6: Net Revenue from Operations | B6: 850 | C6: 4580 | D6: 8350 | E6: =D6*(1+Assumptions!B10) -> 11690 | F6: =E6*(1+Assumptions!C10) -> 15430.8 | G6: =F6*(1+Assumptions!D10) -> 19288.5
A7: Revenue Growth (%) | C7: =(C6-B6)/B6 -> 4.3882353 | D7: =(D6-C6)/C6 -> 0.8231441 | E7: =Assumptions!B10 -> 0.4 | F7: =Assumptions!C10 -> 0.32 | G7: =Assumptions!D10 -> 0.25
A8: II. OPERATING EXPENSES
A9: Fuel & ATF Costs | B9: 580 | C9: 2750 | D9: 4720 | E9: =E6*Assumptions!B13 -> 4968.25 | F9: =F6*Assumptions!C13 -> 6480.936 | G9: =G6*Assumptions!D13 -> 8004.7275
A10: Employee Costs | B10: 190 | C10: 680 | D10: 1240 | E10: =E6*Assumptions!B14 -> 1344.35 | F10: =F6*Assumptions!C14 -> 1697.388 | G10: =G6*Assumptions!D14 -> 2025.2925
A11: Maintenance & Engineering | B11: 95 | C11: 410 | D11: 780 | E11: =E6*Assumptions!B15 -> 935.2 | F11: =F6*Assumptions!C15 -> 1265.3256 | G11: =G6*Assumptions!D15 -> 1639.5225
A12: Airport & Navigation Charges | B12: 120 | C12: 540 | D12: 1050 | E12: =E6*Assumptions!B16 -> 1285.9 | F12: =F6*Assumptions!C16 -> 1666.5264 | G12: =G6*Assumptions!D16 -> 2044.581
A13: Other Operating Expenses | B13: 185 | C13: 630 | D13: 1180 | E13: =E6*Assumptions!B18 -> 1110.55 | F13: =F6*Assumptions!C18 -> 1435.0644 | G13: =G6*Assumptions!D18 -> 1735.965
A14: Total Operating Expenses (excl. Lease Rentals) | B14: =SUM(B9:B13) -> 1170 | C14: =SUM(C9:C13) -> 5010 | D14: =SUM(D9:D13) -> 8970 | E14: =SUM(E9:E13) -> 9644.25 | F14: =SUM(F9:F13) -> 12545.24 | G14: =SUM(G9:G13) -> 15450.088
A15: Aircraft Lease Rentals (Ind AS 116 – EBITDAR add-back) | B15: 210 | C15: 820 | D15: 1480 | E15: =E6*Assumptions!B17 -> 1811.95 | F15: =F6*Assumptions!C17 -> 2314.62 | G15: =G6*Assumptions!D17 -> 2796.8325
A16: EBITDAR | B16: -530 | C16: -1250 | D16: -1100 | E16: =E6-E14 -> 2045.75 | F16: =F6-F14 -> 2885.5596 | G16: =G6-G14 -> 3838.4115
A17: EBITDAR Margin (%) | B17: =B16/B6 -> -0.62352941 | C17: =C16/C6 -> -0.27292576 | D17: =D16/D6 -> -0.13173653 | E17: =E16/E6 -> 0.175 | F17: =F16/F6 -> 0.187 | G17: =G16/G6 -> 0.199
A18: III. DEPRECIATION & AMORTISATION
A19: D&A (incl. ROU amortisation – Ind AS 116) | B19: 180 | C19: 520 | D19: 920 | E19: =E6*Assumptions!B20 -> 1110.55 | F19: =F6*Assumptions!C20 -> 1435.0644 | G19: =G6*Assumptions!D20 -> 1735.965
A20: EBIT (Operating Profit/(Loss)) | B20: -710 | C20: -1770 | D20: -2020 | E20: =E16-E15-E19 -> -876.75 | F20: =F16-F15-F19 -> -864.1248 | G20: =G16-G15-G19 -> -694.386
A21: IV. FINANCE COSTS
A22: Finance Costs (incl. lease interest – Ind AS 116) | B22: 165 | C22: 480 | D22: 860 | E22: =E6*Assumptions!B22 -> 1052.1 | F22: =F6*Assumptions!C22 -> 1311.618 | G22: =G6*Assumptions!D22 -> 1543.08
A23: PROFIT / (LOSS) BEFORE TAX (EBT) | B23: -875 | C23: -2250 | D23: -2880 | E23: =E20-E22 -> -1928.85 | F23: =F20-F22 -> -2175.7428 | G23: =G20-G22 -> -2237.466
A24: V. TAXATION
A25: Income Tax Expense | B25: 0 | C25: 0 | D25: 0 | E25: =MAX(0,E23)*Assumptions!B24 -> 0 | F25: =MAX(0,F23)*Assumptions!C24 -> 0 | G25: =MAX(0,G23)*Assumptions!D24 -> 0
A26: NET PROFIT / (LOSS) AFTER TAX (PAT) | B26: -875 | C26: -2250 | D26: -2880 | E26: =E23-E25 -> -1928.85 | F26: =F23-F25 -> -2175.7428 | G26: =G23-G25 -> -2237.466
A27: PAT Margin (%) | B27: =B26/B6 -> -1.0294118 | C27: =C26/C6 -> -0.49126638 | D27: =D26/D6 -> -0.34491018 | E27: =E26/E6 -> -0.165 | F27: =F26/F6 -> -0.141 | G27: =G26/G6 -> -0.116

Sheet Balance Sheet
A1: AKASA AIR (SNV AVIATION PVT LTD) – PROJECTED BALANCE SHEET (INR Crores)
A2: ⚠ Historical figures are approximate. Balance sheet balances via retained earnings / equity check row. FY26 gap year not modelled. Cash linked from Cash Flow sheet.
A3: Particulars (INR Crores) | B3: FY 2022-23 (Partial/Est.) | C3: FY 2023-24 (Approx.) | D3: FY 2024-25 (Prelim.) | E3: FY 2026-27 (Forecast) | F3: FY 2027-28 (Forecast) | G3: FY 2028-29 (Forecast)
B4: ◄ HISTORICAL (Approximate) ► | E4: ◄ FORECAST ►
A5: ASSETS
A6: A. CURRENT ASSETS
A7: Cash & Cash Equivalents | B7: 4200 | C7: 3100 | D7: 2400 | E7: ='Cash Flow'!E27 -> 4535.0015 | F7: ='Cash Flow'!F27 -> 5456.5245 | G7: ='Cash Flow'!G27 -> 6022.967
A8: Trade Receivables | B8: 35 | C8: 188 | D8: 343 | E8: ='P&L Statement'!E6*Assumptions!B26/365 -> 480.41096 | F8: ='P&L Statement'!F6*Assumptions!C26/365 -> 591.8663 | G8: ='P&L Statement'!G6*Assumptions!D26/365 -> 686.98767
A9: Other Current Assets | B9: 380 | C9: 1100 | D9: 1850 | E9: ='P&L Statement'!E6*Assumptions!B28 -> 876.75 | F9: ='P&L Statement'!F6*Assumptions!C28 -> 1126.4484 | G9: ='P&L Statement'!G6*Assumptions!D28 -> 1350.195
A10: TOTAL CURRENT ASSETS | B10: 4615 | C10: 4388 | D10: 4593 | E10: =SUM(E7:E9) -> 5892.1625 | F10: =SUM(F7:F9) -> 7174.8392 | G10: =SUM(G7:G9) -> 8060.1496
A11: B. NON-CURRENT ASSETS
A12: Right-of-Use (ROU) Assets – Aircraft Leases (Ind AS 116) | B12: 1200 | C12: 4800 | D12: 8500 | E12: =D12+Assumptions!B33*Assumptions!B32-'P&L Statement'!E19 -> 8397.45 | F12: =E12+Assumptions!C33*Assumptions!C32-'P&L Statement'!F19 -> 7962.3856 | G12: =F12+Assumptions!D33*Assumptions!D32-'P&L Statement'!G19 -> 7266.4206
A13: Property, Plant & Equipment (net) | B13: 220 | C13: 610 | D13: 1020 | E13: =D13+Assumptions!B31-D13*0.1 -> 1338 | F13: =E13+Assumptions!C31-E13*0.1 -> 1754.2 | G13: =F13+Assumptions!D31-F13*0.1 -> 2258.78
A14: Other Non-Current Assets (deposits, security deposits) | B14: 180 | C14: 320 | D14: 450 | E14: =D14*1.08 -> 486 | F14: =E14*1.08 -> 524.88 | G14: =F14*1.08 -> 566.8704
A15: TOTAL NON-CURRENT ASSETS | B15: 1600 | C15: 5730 | D15: 9970 | E15: =SUM(E12:E14) -> 10221.45 | F15: =SUM(F12:F14) -> 10241.466 | G15: =SUM(G12:G14) -> 10092.071
A16: TOTAL ASSETS | B16: 6215 | C16: 10118 | D16: 14563 | E16: =E10+E15 -> 16113.612 | F16: =F10+F15 -> 17416.305 | G16: =G10+G15 -> 18152.221
A18: LIABILITIES & EQUITY
A19: C. CURRENT LIABILITIES
A20: Lease Liabilities – Current portion | B20: 220 | C20: 680 | D20: 1150 | E20: =D20*1.15 -> 1322.5 | F20: =E20*1.1 -> 1454.75 | G20: =F20*1.08 -> 1571.13
A21: Trade & Other Payables | B21: 56 | C21: 264 | D21: 453 | E21: ='P&L Statement'!E9*Assumptions!B27/365 -> 517.24247 | F21: ='P&L Statement'!F9*Assumptions!C27/365 -> 710.23956 | G21: ='P&L Statement'!G9*Assumptions!D27/365 -> 921.09193
A22: Other Current Liabilities (deferred revenue, accruals) | B22: 290 | C22: 820 | D22: 1440 | E22: ='P&L Statement'!E6*Assumptions!B29 -> 1402.8 | F22: ='P&L Statement'!F6*Assumptions!C29 -> 1820.8344 | G22: ='P&L Statement'!G6*Assumptions!D29 -> 2218.1775
A23: TOTAL CURRENT LIABILITIES | B23: 566 | C23: 1304 | D23: 2113 | E23: =SUM(E20:E22) -> 3242.5425 | F23: =SUM(F20:F22) -> 3985.824 | G23: =SUM(G20:G22) -> 4710.3994
A24: D. NON-CURRENT LIABILITIES
A25: Lease Liabilities – Non-current (Ind AS 116) | B25: 1130 | C25: 4720 | D25: 8050 | E25: =D25+Assumptions!B33*Assumptions!B32-'P&L Statement'!E22 -> 8005.9 | F25: =E25+Assumptions!C33*Assumptions!C32-'P&L Statement'!F22 -> 7694.282 | G25: =F25+Assumptions!D33*Assumptions!D32-'P&L Statement'!G22 -> 7191.202
A26: Other Non-Current Liabilities | B26: 420 | C26: 980 | D26: 1650 | E26: =D26*1.06 -> 1749 | F26: =E26*1.06 -> 1853.94 | G26: =F26*1.06 -> 1965.1764
A27: TOTAL NON-CURRENT LIABILITIES | B27: 1550 | C27: 5700 | D27: 9700 | E27: =SUM(E25:E26) -> 9754.9 | F27: =SUM(F25:F26) -> 9548.222 | G27: =SUM(G25:G26) -> 9156.3784
A28: E. SHAREHOLDERS' EQUITY
A29: Share Capital & Share Premium | B29: 5100 | C29: 4200 | D29: 2800 | E29: =D29+Assumptions!B34 -> 5300 | F29: =E29+Assumptions!C34 -> 7300 | G29: =F29+Assumptions!D34 -> 8800
A30: Accumulated Deficit / Retained Earnings | B30: -875 | C30: -3125 | D30: -6005 | E30: =D30+'P&L Statement'!E26 -> -7933.85 | F30: =E30+'P&L Statement'!F26 -> -10109.593 | G30: =F30+'P&L Statement'!G26 -> -12347.059
A31: TOTAL EQUITY | B31: 4225 | C31: 1075 | D31: -3205 | E31: =E29+E30 -> -2633.85 | F31: =F29+F30 -> -2809.5928 | G31: =G29+G30 -> -3547.0588
A32: TOTAL LIABILITIES & EQUITY | B32: 6341 | C32: 8079 | D32: 8608 | E32: =E23+E27+E31 -> 10363.592 | F32: =F23+F27+F31 -> 10724.453 | G32: =G23+G27+G31 -> 10319.719
A33: ✔ Balance Check (Assets – Liabilities & Equity) | B33: ⚠ Gap reflects approximate historical BS data. See note below. | E33: =E16-E32 -> 5750.02 | F33: =F16-F32 -> 6691.8516 | G33: =G16-G32 -> 7832.5016
A34: ⚠ BALANCE SHEET MODELLING NOTE: The positive balance check (Assets > L+E) indicates a funding gap. This arises because: (1) historical figures are approximate estimates, not verified ROC filings; (2) pre-delivery payments (PDPs) to Boeing and security deposits are not separately modelled; (3) actual equity tranches and their timing are uncertain. In a fully verified model, insert actual ROC-filed balance sheet figures, add a PDP/deposit line, and adjust equity timing to achieve zero balance check. The gap represents additional financing (equity or debt) implicitly required.

Sheet Cash Flow
A1: AKASA AIR – PROJECTED CASH FLOW STATEMENT – INDIRECT METHOD (INR Crores)
A2: ⚠ Historical CFO/CFI/CFF are approximate. Forecast derived from P&L and BS. FY27 opening cash = FY25 estimated closing cash (FY26 gap year not modelled).
A3: Particulars (INR Crores) | B3: FY 2022-23 (Partial/Est.) | C3: FY 2023-24 (Approx.) | D3: FY 2024-25 (Prelim.) | E3: FY 2026-27 (Forecast) | F3: FY 2027-28 (Forecast) | G3: FY 2028-29 (Forecast)
B4: ◄ HISTORICAL (Approximate) ► | E4: ◄ FORECAST ►
A5: A. CASH FLOW FROM OPERATING ACTIVITIES (CFO)
A6: Net Profit / (Loss) After Tax | B6: -875 | C6: -2250 | D6: -2880 | E6: ='P&L Statement'!E26 -> -1928.85 | F6: ='P&L Statement'!F26 -> -2175.7428 | G6: ='P&L Statement'!G26 -> -2237.466
A7: Add: Depreciation & Amortisation (incl. ROU) | B7: 180 | C7: 520 | D7: 920 | E7: ='P&L Statement'!E19 -> 1110.55 | F7: ='P&L Statement'!F19 -> 1435.0644 | G7: ='P&L Statement'!G19 -> 1735.965
A8: Add: Finance Costs (non-cash lease interest component) | B8: 99 | C8: 288 | D8: 516 | E8: ='P&L Statement'!E22*0.6 -> 631.26 | F8: ='P&L Statement'!F22*0.6 -> 786.9708 | G8: ='P&L Statement'!G22*0.6 -> 925.848
A9: Working Capital Changes
A10: (Increase)/Decrease in Trade Receivables | B10: 0 | C10: -153 | D10: -155 | E10: =-('Balance Sheet'!E8-'Balance Sheet'!D8) -> -137.41096 | F10: =-('Balance Sheet'!F8-'Balance Sheet'!E8) -> -111.45534 | G10: =-('Balance Sheet'!G8-'Balance Sheet'!F8) -> -95.12137
A11: (Increase)/Decrease in Other Current Assets | B11: 0 | C11: -720 | D11: -750 | E11: =-('Balance Sheet'!E9-'Balance Sheet'!D9) -> 973.25 | F11: =-('Balance Sheet'!F9-'Balance Sheet'!E9) -> -249.6984 | G11: =-('Balance Sheet'!G9-'Balance Sheet'!F9) -> -223.7466
A12: Increase/(Decrease) in Trade Payables | B12: 0 | C12: 208 | D12: 189 | E12: ='Balance Sheet'!E21-'Balance Sheet'!D21 -> 64.242466 | F12: ='Balance Sheet'!F21-'Balance Sheet'!E21 -> 192.9971 | G12: ='Balance Sheet'!G21-'Balance Sheet'!F21 -> 210.85237
A13: Increase/(Decrease) in Other Current Liabilities | B13: 0 | C13: 530 | D13: 620 | E13: ='Balance Sheet'!E22-'Balance Sheet'!D22 -> -37.2 | F13: ='Balance Sheet'!F22-'Balance Sheet'!E22 -> 418.0344 | G13: ='Balance Sheet'!G22-'Balance Sheet'!F22 -> 397.3431
A14: NET CASH FROM OPERATING ACTIVITIES (CFO) | B14: -1300 | C14: -1800 | D14: -2200 | E14: =SUM(E6:E13) -> 675.84151 | F14: =SUM(F6:F13) -> 296.17015 | G14: =SUM(G6:G13) -> 713.6745
A15: B. CASH FLOW FROM INVESTING ACTIVITIES (CFI)
A16: Purchase of PPE / Capex | B16: -180 | C16: -420 | D16: -720 | E16: =-Assumptions!B31 -> -420 | F16: =-Assumptions!C31 -> -550 | G16: =-Assumptions!D31 -> -680
A17: Security deposits & other investing | B17: -80 | C17: -120 | D17: -150 | E17: -80 | F17: -120 | G17: -150
A18: NET CASH FROM INVESTING ACTIVITIES (CFI) | B18: -260 | C18: -540 | D18: -870 | E18: =SUM(E16:E17) -> -500 | F18: =SUM(F16:F17) -> -670 | G18: =SUM(G16:G17) -> -830
A19: C. CASH FLOW FROM FINANCING ACTIVITIES (CFF)
A20: Proceeds from Equity Raise | B20: 3500 | C20: 1800 | D20: 800 | E20: =Assumptions!B34 -> 2500 | F20: =Assumptions!C34 -> 2000 | G20: =Assumptions!D34 -> 1500
A21: Payment of Lease Liabilities (principal) | B21: -280 | C21: -650 | D21: -1020 | E21: =-'P&L Statement'!E22*0.4 -> -420.84 | F21: =-'P&L Statement'!F22*0.4 -> -524.6472 | G21: =-'P&L Statement'!G22*0.4 -> -617.232
A22: Other financing (net borrowings / repayments) | B22: -120 | C22: -180 | D22: -200 | E22: -120 | F22: -180 | G22: -200
A23: NET CASH FROM FINANCING ACTIVITIES (CFF) | B23: 3100 | C23: -1030 | D23: -420 | E23: =SUM(E20:E22) -> 1959.16 | F23: =SUM(F20:F22) -> 1295.3528 | G23: =SUM(G20:G22) -> 682.768
A24: D. NET CASH MOVEMENT
A25: Net Increase / (Decrease) in Cash | B25: 1540 | C25: -3370 | D25: -3490 | E25: =E14+E18+E23 -> 2135.0015 | F25: =F14+F18+F23 -> 921.52295 | G25: =G14+G18+G23 -> 566.4425
A26: Opening Cash & Cash Equivalents | B26: 2660 | C26: 4200 | D26: 830 | E26: 2400 | F26: =E27 -> 4535.0015 | G26: =F27 -> 5456.5245
A27: CLOSING CASH & CASH EQUIVALENTS | B27: 4200 | C27: 830 | D27: -2660 | E27: =E26+E25 -> 4535.0015 | F27: =F26+F25 -> 5456.5245 | G27: =G26+G25 -> 6022.967
