Workbook

Sheet Sheet1
A1: Singapore Airlines | J1: Cathay Pacific
B3: IN SGD | J3: in HKD
B4: 2024-2025 | C4: 2023-2024 | D4: 2022-2023 | E4: 2021-2022 | F4: 2020-2021 | J4: 2024-2025 | K4: 2023-2024 | L4: 2022-2023 | M4: 2021-2022 | N4: 2020-2021
A5: Total Revenue (in million) | B5: 19539.8 | C5: 19012.7 | D5: 17774.8 | E5: 7614.8 | F5: 3815.9 | I5: Total Revenue (in million) | J5: 116766 | K5: 104371 | L5: 94485 | M5: 51036 | N5: 45587
A6: Total Expenses | B6: 17830.7 | C6: 16285.2 | D6: 15082.7 | E6: 8224.5 | F6: 6328.4 | I6: Total Expenses | J6: 102693 | K6: 91194 | L6: 81486 | M6: 47565 | N6: 46037
A7: Operating Profit/Loss (in million) | B7: 1709.1 | C7: 2727.5 | D7: 2692.1 | E7: -609.7 | F7: -2512.5 | I7: Operating Profit/Loss (in million) | J7: 14458 | K7: 13928 | L7: 15125 | M7: 3471 | N7: -1443
A8: Profit/Loss Before Taxaction (in million) | B8: 2964.8 | C8: 3037.1 | D8: 2636.8 | E8: -1090 | F8: -4957.2 | I8: Profit/Loss Before Taxaction (in million) | J8: 12310 | K8: 11203 | L8: 10858 | M8: -6115 | N8: -6057
A9: Profit for the Financial Year | B9: 2812.2 | C9: 2695.1 | D9: 2218.9 | I9: Profit/Loss for the Financial Year | J9: 10828 | K9: 9888 | L9: 9790 | M9: -6622 | N9: -5526
A10: Earnings Per Share (in cents) | B10: 89.3 | C10: 63.3 | D10: 35.6 | E10: -16.2 | F10: -102.6 | I10: Earnings Per Share (in cents) | J10: 165.5 | K10: 149.2 | L10: 140.8 | M10: -112.4 | N10: -95.1
A11: Total Assets (in million) | B11: 43086.8 | C11: 44264.7 | D11: 49101.2 | E11: 48671 | F11: 37581.3 | I11: Total Assets (in million) | J11: 154521 | K11: 151998 | L11: 151366 | M11: 154578 | N11: 167730
A12: Net Asset Value per share | B12: 5.27 | C12: 5.49 | D12: 6.68 | E12: 7.55 | F12: 5.36 | I12: Net Asset Value per share | J12: 8.9 | K12: 8.2 | L12: 7.8 | M12: 6.7 | N12: 8.1
A14: sales/asset (in million) | B14: =B5/B11 -> 0.45349852 | C14: =C5/C11 -> 0.42952285 | D14: =D5/D11 -> 0.36200337 | E14: =E5/E11 -> 0.15645456 | F14: =F5/F11 -> 0.1015372 | I14: sales/asset (in million) | J14: =J5/J11 -> 0.75566428 | K14: =K5/K11 -> 0.68666035 | L14: =L5/L11 -> 0.62421548 | M14: =M5/M11 -> 0.33016341 | N14: =N5/N11 -> 0.27178799
A15: sales/employee | B15: 702340 | C15: 742133 | D15: 778947 | E15: 342793 | F15: 149368 | I15: sales/employee (in million) | J15: =J5/J18 -> 3.5383636 | K15: =K5/K18 -> 3.4674751 | L15: =L5/L18 -> 3.969958 | M15: =M5/M18 -> 2.4073585 | N15: =N5/N18 -> 2.1105093
A16: (in million) | B16: =B5/B18 -> 0.70233996 | C16: =C5/C18 -> 0.74213279 | D16: =D5/D18 -> 0.77894737 | E16: =E5/E18 -> 0.34279283 | F16: =F5/F18 -> 0.14936783
A18: Employee Count | B18: 27821 | C18: 25619 | D18: 22819 | E18: 22214 | F18: 25547 | I18: Employee Count | J18: 33000 | K18: 30100 | L18: 23800 | M18: 21200 | N18: 21600
B20: Singapore Airlines | J20: Cathay Pacific
B22: IN INR (converted using the exchange rate of 1 SGD = 74.45 INR | J22: IN INR (converted using the exchange rate of 1HKD = 12.12 INR
B23: 2024-2025 | C23: 2023-2024 | D23: 2022-2023 | E23: 2021-2022 | F23: 2020-2021 | J23: 2024-2025 | K23: 2023-2024 | L23: 2022-2023 | M23: 2021-2022 | N23: 2020-2021
A24: Total Revenue (in million) | B24: {=B5:F16*74.45} -> 1454738.1 | C24: 1415495.5 | D24: 1323333.9 | E24: 566921.86 | F24: 284093.76 | I24: Total Revenue (in million) | J24: {=J5:N15*12.12} -> 1415203.9 | K24: 1264976.5 | L24: 1145158.2 | M24: 618556.32 | N24: 552514.44
A25: Total Expenses | B25: 1327495.6 | C25: 1212433.1 | D25: 1122907 | E25: 612314.03 | F25: 471149.38 | I25: Total Expenses | J25: 1244639.2 | K25: 1105271.3 | L25: 987610.32 | M25: 576487.8 | N25: 557968.44
A26: Operating Profit/Loss (in million) | B26: 127242.49 | C26: 203062.38 | D26: 200426.85 | E26: -45392.165 | F26: -187055.62 | I26: Operating Profit/Loss (in million) | J26: 175230.96 | K26: 168807.36 | L26: 183315 | M26: 42068.52 | N26: -17489.16
A27: Profit/Loss Before Taxaction (in million) | B27: 220729.36 | C27: 226112.1 | D27: 196309.76 | E27: -81150.5 | F27: -369063.54 | I27: Profit/Loss Before Taxaction (in million) | J27: 149197.2 | K27: 135780.36 | L27: 131598.96 | M27: -74113.8 | N27: -73410.84
A28: Profit for the Financial Year | B28: 209368.29 | C28: 200650.2 | D28: 165197.11 | E28: 0 | F28: 0 | I28: Profit/Loss for the Financial Year | J28: 131235.36 | K28: 119842.56 | L28: 118654.8 | M28: -80258.64 | N28: -66975.12
A29: Earnings Per Share (in cents) | B29: 6648.385 | C29: 4712.685 | D29: 2650.42 | E29: -1206.09 | F29: -7638.57 | I29: Earnings Per Share (in cents) | J29: 2005.86 | K29: 1808.304 | L29: 1706.496 | M29: -1362.288 | N29: -1152.612
A30: Total Assets (in million) | B30: 3207812.3 | C30: 3295506.9 | D30: 3655584.3 | E30: 3623556 | F30: 2797927.8 | I30: Total Assets (in million) | J30: 1872794.5 | K30: 1842215.8 | L30: 1834555.9 | M30: 1873485.4 | N30: 2032887.6
A31: Net Asset Value per share | B31: 392.3515 | C31: 408.7305 | D31: 497.326 | E31: 562.0975 | F31: 399.052 | I31: Net Asset Value per share | J31: 107.868 | K31: 99.384 | L31: 94.536 | M31: 81.204 | N31: 98.172
B32: 0 | C32: 0 | D32: 0 | E32: 0 | F32: 0 | J32: 0 | K32: 0 | L32: 0 | M32: 0 | N32: 0
A33: sales/asset (in million) | B33: 33.762965 | C33: 31.977976 | D33: 26.951151 | E33: 11.648042 | F33: 7.5594446 | I33: sales/asset (in million) | J33: 9.1586511 | K33: 8.3223235 | L33: 7.5654916 | M33: 4.0015806 | N33: 3.2940705
A34: sales/employee | B34: 52289213 | C34: 55251802 | D34: 57992604 | E34: 25520939 | F34: 11120448 | I34: sales/employee (in million) | J34: 42.884967 | K34: 42.025798 | L34: 48.115891 | M34: 29.177185 | N34: 25.579372
A35: (in million) | B35: 52.28921 | C35: 55.251786 | D35: 57.992632 | E35: 25.520926 | F35: 11.120435
A37: Employee Count | B37: 27821 | C37: 25619 | D37: 22819 | E37: 22214 | F37: 25547 | I37: Employee Count | J37: 33000 | K37: 30100 | L37: 23800 | M37: 21200 | N37: 21600

Sheet Sheet2
A1: Singapore Airlines | J1: Cathay Pacific
A3: IN INR (in millions) (converted using the exchange rate of 1 SGD = 74.45 INR) | J3: IN INR (in millions) (converted using the exchange rate of 1 HKD = 12.12 INR)
B5: 2025 | C5: 2024 | D5: 2023 | E5: 2022 | F5: 2021 | K5: 2025 | L5: 2024 | M5: 2023 | N5: 2022 | O5: 2021
A6: Total Revenue | B6: 1454738.1 | C6: 1415495.5 | D6: 1323333.9 | E6: 566921.86 | F6: 284093.76 | J6: Total Revenue | K6: =Sheet1!J5*12.12 -> 1415203.9 | L6: =Sheet1!K5*12.12 -> 1264976.5 | M6: =Sheet1!L5*12.12 -> 1145158.2 | N6: =Sheet1!M5*12.12 -> 618556.32 | O6: =Sheet1!N5*12.12 -> 552514.44
A7: Total Expenses | B7: 1327495.6 | C7: 1212433.1 | D7: 1122907 | E7: 612314.03 | F7: 471149.38 | J7: Total Expenses | K7: =Sheet1!J6*12.12 -> 1244639.2 | L7: =Sheet1!K6*12.12 -> 1105271.3 | M7: =Sheet1!L6*12.12 -> 987610.32 | N7: =Sheet1!M6*12.12 -> 576487.8 | O7: =Sheet1!N6*12.12 -> 557968.44
A8: Operating Profit/Loss | B8: 127242.5 | C8: 203062.38 | D8: 200426.85 | E8: -45392.17 | F8: =Sheet1!F7*74.45 -> -187055.62 | J8: Operating Profit/Loss | K8: =Sheet1!J7*12.12 -> 175230.96 | L8: =Sheet1!K7*12.12 -> 168807.36 | M8: =Sheet1!L7*12.12 -> 183315 | N8: =Sheet1!M7*12.12 -> 42068.52 | O8: =Sheet1!N7*12.12 -> -17489.16
A9: Profit/Loss Before Taxaction | B9: =Sheet1!B8*74.45 -> 220729.36 | C9: =Sheet1!C8*74.45 -> 226112.1 | D9: =Sheet1!D8*74.45 -> 196309.76 | E9: =Sheet1!E8*74.45 -> -81150.5 | F9: =Sheet1!F8*74.45 -> -369063.54 | J9: Profit/Loss Before Taxaction | K9: =Sheet1!J8*12.12 -> 149197.2 | L9: =Sheet1!K8*12.12 -> 135780.36 | M9: =Sheet1!L8*12.12 -> 131598.96 | N9: =Sheet1!M8*12.12 -> -74113.8 | O9: =Sheet1!N8*12.12 -> -73410.84
A10: Profit/Loss for the Financial Year | B10: =Sheet1!B9*74.45 -> 209368.29 | C10: =Sheet1!C9*74.45 -> 200650.2 | D10: =Sheet1!D9*74.45 -> 165197.11 | J10: Profit/Loss for the Financial Year | K10: =Sheet1!J9*12.12 -> 131235.36 | L10: =Sheet1!K9*12.12 -> 119842.56 | M10: =Sheet1!L9*12.12 -> 118654.8 | N10: =Sheet1!M9*12.12 -> -80258.64 | O10: =Sheet1!N9*12.12 -> -66975.12
A11: Earnings Per Share (in INR) | B11: =Sheet1!B10*74.45/100 -> 66.48385 | C11: =Sheet1!C10*74.45/100 -> 47.12685 | D11: =Sheet1!D10*74.45/100 -> 26.5042 | E11: =Sheet1!E10*74.45/100 -> -12.0609 | F11: =Sheet1!F10*74.45/100 -> -76.3857 | J11: Earnings Per Share (in INR) | K11: =Sheet1!J10*12.12/100 -> 20.0586 | L11: =Sheet1!K10*12.12/100 -> 18.08304 | M11: =Sheet1!L10*12.12/100 -> 17.06496 | N11: =Sheet1!M10*12.12/100 -> -13.62288 | O11: =Sheet1!N10*12.12/100 -> -11.52612
A12: Total Assets | B12: =Sheet1!B11*74.45 -> 3207812.3 | C12: =Sheet1!C11*74.45 -> 3295506.9 | D12: =Sheet1!D11*74.45 -> 3655584.3 | E12: =Sheet1!E11*74.45 -> 3623556 | F12: =Sheet1!F11*74.45 -> 2797927.8 | J12: Total Assets | K12: =Sheet1!J11*12.12 -> 1872794.5 | L12: =Sheet1!K11*12.12 -> 1842215.8 | M12: =Sheet1!L11*12.12 -> 1834555.9 | N12: =Sheet1!M11*12.12 -> 1873485.4 | O12: =Sheet1!N11*12.12 -> 2032887.6
A13: Employee Count | B13: 27821 | C13: 25619 | D13: 22819 | E13: 22214 | F13: 25547 | J13: Employee Count | K13: 33000 | L13: 30100 | M13: 23800 | N13: 21200 | O13: 21600
A15: Calculated Values
J16: Sales/Asset | K16: =K6/K12 -> 0.75566428 | L16: =L6/L12 -> 0.68666035 | M16: =M6/M12 -> 0.62421548 | N16: =N6/N12 -> 0.33016341 | O16: =O6/O12 -> 0.27178799
A17: Sales/Asset | B17: =B6/B12 -> 0.45349852 | C17: =C6/C12 -> 0.42952285 | D17: =D6/D12 -> 0.36200337 | E17: =E6/E12 -> 0.15645456 | F17: =F6/F12 -> 0.1015372 | J17: Percentage Change in Sales/Asset | K17: =(K16-L16)/L16% -> 10.049208 | L17: =(L16-M16)/M16% -> 10.003737 | M17: =(M16-N16)/N16% -> 89.062583 | N17: =(N16-O16)/O16% -> 21.478293
A18: Percentage Change in Sales/Asset | B18: =(B17-C17)/C17% -> 5.5819312 | C18: =(C17-D17)/D17% -> 18.651615 | D18: =(D17-E17)/E17% -> 131.37924 | E18: =(E17-F17)/F17% -> 54.085949 | J18: Total Percentage Change in Sales/Asset in 5 years | K18: =(K16-O16)/O16% -> 178.03446
A19: Total Percentage Change in Sales/Asset in 5 years | B19: =(B17-F17)/F17% -> 346.63287 | J19: Sales/Employee | K19: =K6/K13 -> 42.884967 | L19: =L6/L13 -> 42.025798 | M19: =M6/M13 -> 48.115891 | N19: =N6/N13 -> 29.177185 | O19: =O6/O13 -> 25.579372
A20: Sales/Employee | B20: =B6/B13 -> 52.28921 | C20: =C6/C13 -> 55.251787 | D20: =D6/D13 -> 57.992632 | E20: =E6/E13 -> 25.520926 | F20: =F6/F13 -> 11.120435 | J20: Percentage Change in Sales/Employee | K20: =(K19-L19)/L19% -> 2.0443854 | L20: =(L19-M19)/M19% -> -12.657134 | M20: =(M19-N19)/N19% -> 64.909298 | N20: =(N19-O19)/O19% -> 14.065289
A21: Percentage Change in Sales/Employee | B21: =(B20-C20)/C20% -> -5.3619562 | C21: =(C20-D20)/D20% -> -4.7261953 | D21: =(D20-E20)/E20% -> 127.2356 | E21: =(E20-F20)/F20% -> 129.49575
A23: Notes
A25: Sales/Asset = Total Revenue/Total Assets
A26: Sales/Employee = Total Revenue/Employee Count
A27: Operating Profit/Loss = Total Revenue - Total Expenses
