Workbook

Sheet Given
B2: Liz Motor Corp. -- Base Case Assumptions
B4: Year | C4: 2023 | D4: 2024 | E4: 2025 | F4: 2026 | G4: 2027 | H4: 2028 | I4: 2029 | J4: 2030 | K4: 2031 | L4: 2032 | M4: 2033 | N4: 2034 | O4: 2035
B5: Period (t) | C5: 0 | D5: 1 | E5: 2 | F5: 3 | G5: 4 | H5: 5 | I5: 6 | J5: 7 | K5: 8 | L5: 9 | M5: 10 | N5: 11 | O5: 12
B6: Base-case Cash Flow ($M) | C6: -800 | D6: -20 | E6: -20 | F6: -20 | G6: -20 | H6: 200 | I6: 200 | J6: 200 | K6: 200 | L6: 200 | M6: 200 | N6: 200 | O6: 200
B9: Base after-tax cost of debt (hurdle rate) | C9: 0.08

Sheet Q1
B2: Question 1 -- Is Liz Well Positioned for Success?
B4: Strengths
B5: Liz has aspired to EV market leadership since its 2012 founding, expanding from cars into battery-powered buses and trucks, with healthy sales growth driven by younger buyers.
B7: As a young company, Liz carries none of the legacy costs that slow down incumbents: no large dealer network, no entrenched unions, and no fossil-fuel business it has to protect while it transitions.
B9: Liz has secured $3.5 billion in financing to launch 20 new EV models by 2027 across factories in the US, Canada and China.
B11: Liz will manufacture its own batteries and is first to use solid-state battery technology (a 39% cut in battery-related carbon footprint), ahead of any major competitor.
B13: Regulatory tailwinds favour EV investment broadly: the US, EU and China have all committed to steep emissions cuts over the next decade.
B15: Weaknesses and risks
B16: Sales growth is decelerating sharply, from 26% in 2021 to 17% in 2022, as the EV market fills up with legacy automakers.
B18: Liz's 2022 ESG rankings were weak enough to drop the stock price 6.2% in a single reaction, and the board has demanded a quick turnaround.
B20: The $3.5B financing commitment plus this project's own $800M+ outlay is high capital intensity, and solid-state battery technology is unproven at scale.
B22: Liz is exposed to interest-rate risk, a Fed hike raises its cost of debt and technology risk, a hydrogen breakthrough could displace solid-state batteries.
... B25: Liz is reasonably well positioned, but not comfortably so. Its structural advantages (no legacy business, secured financing, vertical integration into batteries) and the EV regulatory tailwind are real. But the two things that made Liz distinctive, fast growth and a clean ESG story, are both under pressure at once. This project answers both problems directly, which is why it matters strategically even before the numbers are examined.

Sheet Q2
B2: Question 2 -- What Hurdle Rate Should Be Used?
B4: Rate used
B5: Anthony is financing this specific project with debt, and the case gives its after-tax cost of debt directly: 8% in the base case (7.5% with a green bond, 8.5% if the Fed keeps raising rates). Because the case ties this project's financing to debt and gives no cost of equity, beta, or target capital structure, the after-tax cost of debt, 8%, is used as the hurdle rate throughout this assignment.
B7: Caveat for the board
B8: Per the course WACC formula, WACC = (E/V) x Ke + (D/V) x Kd x (1 - T), the theoretically correct discount rate for a project of average risk blends the cost of equity and the after-tax cost of debt, and equity is almost always priced above debt. Using only the after-tax cost of debt is a conservative, project-specific simplification, not Liz's corporate WACC, and it may understate the true risk-adjusted return the project needs to clear.

Sheet Q3
B2: Question 3 -- Base Model: NPV, IRR, PI, Payback
B4: Year | C4: 2023 | D4: 2024 | E4: 2025 | F4: 2026 | G4: 2027 | H4: 2028 | I4: 2029 | J4: 2030 | K4: 2031 | L4: 2032 | M4: 2033 | N4: 2034 | O4: 2035
B5: Period (t) | C5: 0 | D5: 1 | E5: 2 | F5: 3 | G5: 4 | H5: 5 | I5: 6 | J5: 7 | K5: 8 | L5: 9 | M5: 10 | N5: 11 | O5: 12
B6: Cash Flow ($M) | C6: =Given!C6 -> -800 | D6: =Given!D6 -> -20 | E6: =Given!E6 -> -20 | F6: =Given!F6 -> -20 | G6: =Given!G6 -> -20 | H6: =Given!H6 -> 200 | I6: =Given!I6 -> 200 | J6: =Given!J6 -> 200 | ... O6: =Given!O6 -> 200
B7: Discount Factor = 1/(1+r)^t | C7: =1/(1+$C$16)^C5 -> 1 | D7: =1/(1+$C$16)^D5 -> 0.92592593 | E7: =1/(1+$C$16)^E5 -> 0.85733882 | F7: =1/(1+$C$16)^F5 -> 0.79383224 | G7: =1/(1+$C$16)^G5 -> 0.73502985 | H7: =1/(1+$C$16)^H5 -> 0.6805832 | I7: =1/(1+$C$16)^I5 -> 0.63016963 | J7: =1/(1+$C$16)^J5 -> 0.5834904 | ... O7: =1/(1+$C$16)^O5 -> 0.39711376
B8: PV of Cash Flow ($M) | C8: =C6*C7 -> -800 | D8: =D6*D7 -> -18.518519 | E8: =E6*E7 -> -17.146776 | F8: =F6*F7 -> -15.876645 | G8: =G6*G7 -> -14.700597 | H8: =H6*H7 -> 136.11664 | I8: =I6*I7 -> 126.03393 | J8: =J6*J7 -> 116.69808 | ... O8: =O6*O7 -> 79.422752
B9: Cumulative Cash Flow ($M) | C9: =SUM($C6:C6) -> -800 | D9: =SUM($C6:D6) -> -820 | E9: =SUM($C6:E6) -> -840 | F9: =SUM($C6:F6) -> -860 | G9: =SUM($C6:G6) -> -880 | H9: =SUM($C6:H6) -> -680 | I9: =SUM($C6:I6) -> -480 | J9: =SUM($C6:J6) -> -280 | ... O9: =SUM($C6:O6) -> 720
B10: Cumulative Discounted CF ($M) | C10: =SUM($C8:C8) -> -800 | D10: =SUM($C8:D8) -> -818.51852 | E10: =SUM($C8:E8) -> -835.66529 | F10: =SUM($C8:F8) -> -851.54194 | G10: =SUM($C8:G8) -> -866.24254 | H10: =SUM($C8:H8) -> -730.1259 | I10: =SUM($C8:I8) -> -604.09197 | J10: =SUM($C8:J8) -> -487.39389 | ... O10: =SUM($C8:O8) -> -21.452301
B13: NPV ($M) | C13: =SUM(C8:O8) -> -21.452301
B16: Discount rate (hurdle rate) | C16: =Given!C9 -> 0.08
B20: IRR (rate that sets NPV = 0) | C20: =IRR(C6:O6) -> 0.076586755
B21: PV of inflows ($M) | C21: =SUMIF(C8:O8,">0") -> 844.79024
B22: PV of outflows ($M) | C22: =-SUMIF(C8:O8,"<0") -> 866.24254
B23: Profitability Index, PI = PV(inflows)/PV(outflows) | C23: =C21/C22 -> 0.97523523
B24: Payback period, undiscounted (years) | C24: =SUMPRODUCT(--(C9:O9<0))-1+(-INDEX(C9:O9,SUMPRODUCT(--(C9:O9<0))))/INDEX(C6:O6,SUMPRODUCT(--(C9:O9<0))+1) -> 8.4
B25: Discounted payback period (years) | C25: =IF(COUNTIF(C10:O10,"<0")=13,"Not recovered in 12 yrs",SUMPRODUCT(--(C10:O10<0))-1+(-INDEX(C10:O10,SUMPRODUCT(--(C10:O10<0))))/INDEX(C8:O8,SUMPRODUCT(--(C10:O10<0))+1)) -> Not recovered in 12 yrs

Sheet Q4-B
B2: Scenario B (from case) -- Green Bond Financing: Kd = 7.5%
B4: Year | C4: 2023 | D4: 2024 | E4: 2025 | F4: 2026 | G4: 2027 | H4: 2028 | I4: 2029 | J4: 2030 | K4: 2031 | L4: 2032 | M4: 2033 | N4: 2034 | O4: 2035
B5: Period (t) | C5: 0 | D5: 1 | E5: 2 | F5: 3 | G5: 4 | H5: 5 | I5: 6 | J5: 7 | K5: 8 | L5: 9 | M5: 10 | N5: 11 | O5: 12
B6: Cash Flow ($M) | C6: =Given!C6 -> -800 | D6: =Given!D6 -> -20 | E6: =Given!E6 -> -20 | F6: =Given!F6 -> -20 | G6: =Given!G6 -> -20 | H6: =Given!H6 -> 200 | I6: =Given!I6 -> 200 | J6: =Given!J6 -> 200 | ... O6: =Given!O6 -> 200
B7: Discount Factor = 1/(1+r)^t | C7: =1/(1+$C$21)^C5 -> 1 | D7: =1/(1+$C$21)^D5 -> 0.93023256 | E7: =1/(1+$C$21)^E5 -> 0.86533261 | F7: =1/(1+$C$21)^F5 -> 0.80496057 | G7: =1/(1+$C$21)^G5 -> 0.74880053 | H7: =1/(1+$C$21)^H5 -> 0.69655863 | I7: =1/(1+$C$21)^I5 -> 0.64796152 | J7: =1/(1+$C$21)^J5 -> 0.6027549 | ... O7: =1/(1+$C$21)^O5 -> 0.41985413
B8: PV of Cash Flow ($M) | C8: =C6*C7 -> -800 | D8: =D6*D7 -> -18.604651 | E8: =E6*E7 -> -17.306652 | F8: =F6*F7 -> -16.099211 | G8: =G6*G7 -> -14.976011 | H8: =H6*H7 -> 139.31173 | I8: =I6*I7 -> 129.5923 | J8: =J6*J7 -> 120.55098 | ... O8: =O6*O7 -> 83.970826
B13: NPV ($M) | C13: =SUM(C8:O8) -> 10.203876
B18: Variable changed vs. base case
B19: Variable changed: discount rate, 8% -> 7.5%.
B20: Business impact: cheaper debt alone turns NPV from -$21.45M to +$10.20M. This is a financing choice fully within Liz's control, and on these numbers it is what flips the accept/reject decision.
B21: Discount rate (hurdle rate) | C21: 0.075

Sheet Q4 - C
B2: Scenario C (from case) -- CBAM Tailwind: Inflows Rise to $220M/yr
B4: Year | C4: 2023 | D4: 2024 | E4: 2025 | F4: 2026 | G4: 2027 | H4: 2028 | I4: 2029 | J4: 2030 | K4: 2031 | L4: 2032 | M4: 2033 | N4: 2034 | O4: 2035
B5: Period (t) | C5: 0 | D5: 1 | E5: 2 | F5: 3 | G5: 4 | H5: 5 | I5: 6 | J5: 7 | K5: 8 | L5: 9 | M5: 10 | N5: 11 | O5: 12
B6: Cash Flow ($M) | C6: =Given!C6 -> -800 | D6: =Given!D6 -> -20 | E6: =Given!E6 -> -20 | F6: =Given!F6 -> -20 | G6: =Given!G6 -> -20 | H6: 220 | I6: 220 | J6: 220 | K6: 220 | L6: 220 | M6: 220 | N6: 220 | O6: 220
B7: Discount Factor = 1/(1+r)^t | C7: =1/(1+$C$19)^C5 -> 1 | D7: =1/(1+$C$19)^D5 -> 0.92592593 | E7: =1/(1+$C$19)^E5 -> 0.85733882 | F7: =1/(1+$C$19)^F5 -> 0.79383224 | G7: =1/(1+$C$19)^G5 -> 0.73502985 | H7: =1/(1+$C$19)^H5 -> 0.6805832 | I7: =1/(1+$C$19)^I5 -> 0.63016963 | J7: =1/(1+$C$19)^J5 -> 0.5834904 | ... O7: =1/(1+$C$19)^O5 -> 0.39711376
B8: PV of Cash Flow ($M) | C8: =C6*C7 -> -800 | D8: =D6*D7 -> -18.518519 | E8: =E6*E7 -> -17.146776 | F8: =F6*F7 -> -15.876645 | G8: =G6*G7 -> -14.700597 | H8: =H6*H7 -> 149.7283 | I8: =I6*I7 -> 138.63732 | J8: =J6*J7 -> 128.36789 | ... O8: =O6*O7 -> 87.365027
B13: NPV ($M) | C13: =SUM(C8:O8) -> 63.026722
B16: Variable changed vs. base case
B17: Variable changed: annual inflow, $200M -> $220M for 2028-2035
B18: Business impact: adds about $84.5M of NPV. This upside is exogenous (EU carbon policy) and arrives from 2026, so it needs monitoring rather than action.
B19: Discount rate (hurdle rate) | C19: =Given!C9 -> 0.08

Sheet Q4 - D
B2: Scenario D (from case) -- Sale of Technology in Year 12 for $100M
B4: Year | C4: 2023 | D4: 2024 | E4: 2025 | F4: 2026 | G4: 2027 | H4: 2028 | I4: 2029 | J4: 2030 | K4: 2031 | L4: 2032 | M4: 2033 | N4: 2034 | O4: 2035
B5: Period (t) | C5: 0 | D5: 1 | E5: 2 | F5: 3 | G5: 4 | H5: 5 | I5: 6 | J5: 7 | K5: 8 | L5: 9 | M5: 10 | N5: 11 | O5: 12
B6: Cash Flow ($M) | C6: =Given!C6 -> -800 | D6: =Given!D6 -> -20 | E6: =Given!E6 -> -20 | F6: =Given!F6 -> -20 | G6: =Given!G6 -> -20 | H6: =Given!H6 -> 200 | I6: =Given!I6 -> 200 | J6: =Given!J6 -> 200 | ... N6: =Given!N6 -> 200 | O6: =Given!O6+100 -> 300
B7: Discount Factor = 1/(1+r)^t | C7: =1/(1+$C$21)^C5 -> 1 | D7: =1/(1+$C$21)^D5 -> 0.92592593 | E7: =1/(1+$C$21)^E5 -> 0.85733882 | F7: =1/(1+$C$21)^F5 -> 0.79383224 | G7: =1/(1+$C$21)^G5 -> 0.73502985 | H7: =1/(1+$C$21)^H5 -> 0.6805832 | I7: =1/(1+$C$21)^I5 -> 0.63016963 | J7: =1/(1+$C$21)^J5 -> 0.5834904 | ... O7: =1/(1+$C$21)^O5 -> 0.39711376
B8: PV of Cash Flow ($M) | C8: =C6*C7 -> -800 | D8: =D6*D7 -> -18.518519 | E8: =E6*E7 -> -17.146776 | F8: =F6*F7 -> -15.876645 | G8: =G6*G7 -> -14.700597 | H8: =H6*H7 -> 136.11664 | I8: =I6*I7 -> 126.03393 | J8: =J6*J7 -> 116.69808 | ... O8: =O6*O7 -> 119.13413
B13: NPV ($M) | C13: =SUM(C8:O8) -> 18.259074
B18: Variable changed vs. base case
B19: Variable changed: year-12 cash flow, +$100M salvage
B20: Business impact: adds about $39.7M of NPV and gives Liz a fallback exit if the technology's standalone economics weaken later.
B21: Discount rate (hurdle rate) | C21: =Given!C9 -> 0.08

Sheet Q4 - Custom1
B2: Scenario 4 (our own) -- Severe Rate Shock: Kd = 12%
B4: Year | C4: 2023 | D4: 2024 | E4: 2025 | F4: 2026 | G4: 2027 | H4: 2028 | I4: 2029 | J4: 2030 | K4: 2031 | L4: 2032 | M4: 2033 | N4: 2034 | O4: 2035
B5: Period (t) | C5: 0 | D5: 1 | E5: 2 | F5: 3 | G5: 4 | H5: 5 | I5: 6 | J5: 7 | K5: 8 | L5: 9 | M5: 10 | N5: 11 | O5: 12
B6: Cash Flow ($M) | C6: =Given!C6 -> -800 | D6: =Given!D6 -> -20 | E6: =Given!E6 -> -20 | F6: =Given!F6 -> -20 | G6: =Given!G6 -> -20 | H6: =Given!H6 -> 200 | I6: =Given!I6 -> 200 | J6: =Given!J6 -> 200 | ... O6: =Given!O6 -> 200
B7: Discount Factor = 1/(1+r)^t | C7: =1/(1+$C$19)^C5 -> 1 | D7: =1/(1+$C$19)^D5 -> 0.89285714 | E7: =1/(1+$C$19)^E5 -> 0.79719388 | F7: =1/(1+$C$19)^F5 -> 0.71178025 | G7: =1/(1+$C$19)^G5 -> 0.63551808 | H7: =1/(1+$C$19)^H5 -> 0.56742686 | I7: =1/(1+$C$19)^I5 -> 0.50663112 | J7: =1/(1+$C$19)^J5 -> 0.45234922 | ... O7: =1/(1+$C$19)^O5 -> 0.25667509
B8: PV of Cash Flow ($M) | C8: =C6*C7 -> -800 | D8: =D6*D7 -> -17.857143 | E8: =E6*E7 -> -15.943878 | F8: =F6*F7 -> -14.235605 | G8: =G6*G7 -> -12.710362 | H8: =H6*H7 -> 113.48537 | I8: =I6*I7 -> 101.32622 | J8: =J6*J7 -> 90.469843 | ... O8: =O6*O7 -> 51.335019
B13: NPV ($M) | C13: =SUM(C8:O8) -> -229.34201
B16: Variable changed vs. base case
B17: Variable changed: discount rate, 8% -> 12% (case only goes to 8.5%)
B18: Business impact: NPV falls to -$229.34M, a $207.9M swing. A severe financing shock alone would make this an unambiguous rejection, showing how exposed the decision still is to interest-rate conditions even after a green bond is ruled out.
B19: Discount rate (hurdle rate) | C19: 0.12

Sheet Q4 - Custom2
B2: Scenario 5 (our own) -- Hydrogen Breakthrough at 10% Probability
B4: Year | C4: 2023 | D4: 2024 | E4: 2025 | F4: 2026 | G4: 2027 | H4: 2028 | I4: 2029 | J4: 2030 | K4: 2031 | L4: 2032 | M4: 2033 | N4: 2034 | O4: 2035
B5: Period (t) | C5: 0 | D5: 1 | E5: 2 | F5: 3 | G5: 4 | H5: 5 | I5: 6 | J5: 7 | K5: 8 | L5: 9 | M5: 10 | N5: 11 | O5: 12
B6: Cash Flow ($M) | C6: =Given!C6 -> -800 | D6: =Given!D6 -> -20 | E6: =Given!E6 -> -20 | F6: =Given!F6 -> -20 | G6: =Given!G6 -> -20 | H6: =Given!H6 -> 200 | I6: =Given!I6 -> 200 | J6: =Given!J6 -> 200 | ... M6: =Given!M6 -> 200 | N6: 0 | O6: 0
B7: Discount Factor = 1/(1+r)^t | C7: =1/(1+$C$20)^C5 -> 1 | D7: =1/(1+$C$20)^D5 -> 0.92592593 | E7: =1/(1+$C$20)^E5 -> 0.85733882 | F7: =1/(1+$C$20)^F5 -> 0.79383224 | G7: =1/(1+$C$20)^G5 -> 0.73502985 | H7: =1/(1+$C$20)^H5 -> 0.6805832 | I7: =1/(1+$C$20)^I5 -> 0.63016963 | J7: =1/(1+$C$20)^J5 -> 0.5834904 | ... O7: =1/(1+$C$20)^O5 -> 0.39711376
B8: PV of Cash Flow ($M) | C8: =C6*C7 -> -800 | D8: =D6*D7 -> -18.518519 | E8: =E6*E7 -> -17.146776 | F8: =F6*F7 -> -15.876645 | G8: =G6*G7 -> -14.700597 | H8: =H6*H7 -> 136.11664 | I8: =I6*I7 -> 126.03393 | J8: =J6*J7 -> 116.69808 | ... O8: =O6*O7 -> 0
B13: NPV ($M) | C13: =SUM(C8:O8) -> -186.65163
B15: Probability of this outcome | C15: 0.1
B16: Probability of base case holding | C16: =1-C15 -> 0.9
B17: NPV, base case (12-yr life) ($M) | C17: ='Q3'!C13 -> -21.452301
B18: Expected NPV = P(short)xNPV(short) + P(base)xNPV(base) ($M) | C18: =C15*C13+C16*C17 -> -37.972234
B20: Discount rate (hurdle rate) | C20: =Given!C9 -> 0.08
B23: Variable changed vs. base case
B24: Variable changed: probability of the shortened-life outcome, 30% -> 10%
B25: Business impact: expected NPV still falls to -$37.97M, $16.5M worse than base. Even a much less likely hydrogen breakthrough is costly, so this risk deserves active monitoring at almost any probability above zero.

Sheet Summary
B2: Question 4 -- Sensitivity Summary: 3 Case Scenarios + 2 Custom Scenarios
B4: Scenario | C4: NPV ($M) | D4: Delta vs. base ($M) | E4: Variable changed | F4: Business impact
B5: Base case (8% hurdle) | C5: ='Q3'!C13 -> -21.452301 | D5: n/a | E5: n/a | F5: Reference point (see Q3 sheet for IRR, PI, payback)
B6: 1. Green bond, Kd=7.5% (case) | C6: ='Q4-B'!C13 -> 10.203876 | D6: =C6-C5 -> 31.656177 | E6: Discount rate: 8% -> 7.5% | F6: Turns NPV positive; a financing choice within Liz's control
B7: 2. CBAM, $220M/yr (case) | C7: ='Q4 - C'!C13 -> 63.026722 | D7: =C7-C5 -> 84.479024 | E7: Inflows: $200M -> $220M/yr | F7: Regulatory upside, adds ~$84M; monitor EU rules, no action needed
B8: 3. Sale of tech, +$100M (case) | C8: ='Q4 - D'!C13 -> 18.259074 | D8: =C8-C5 -> 39.711376 | E8: +$100M salvage, year 12 | F8: Adds ~$40M; a fallback exit if tech underperforms
B9: 4. Rate shock, Kd=12% (ours) | C9: ='Q4 - Custom1'!C13 -> -229.34201 | D9: =C9-C5 -> -207.88971 | E9: Discount rate: 8% -> 12% | F9: Wipes out the project; shows financing risk is not fully removed by a green bond
B10: 5. Hydrogen, 10% probability (ours) | C10: ='Q4 - Custom2'!C18 -> -37.972234 | D10: =C10-C5 -> -16.519932 | E10: Probability: 30% -> 10% | F10: Still costs ~$16.5M expected value; worth monitoring at any real probability

Sheet Q5
B2: Question 5 -- Recommendation to the CEO and Board
B4: Where the numbers land
B5: On a strict base-case test, the project is a marginal reject: NPV is slightly negative (-$21.45M), IRR (7.66%) sits just under the 8% hurdle rate, and PI is just under 1.0.
B7: The financing decision alone can flip this: moving to a green bond turns NPV positive by over $30M, and that choice is within Liz's control.
B9: A regulatory tailwind already in motion (CBAM) and the option to sell the technology both push NPV comfortably positive.
B11: The two scenarios we built ourselves show the downside is not limited to the case's own numbers: a severe rate shock (12%) wipes the project out, and even a scaled-down hydrogen risk (10% probability instead of 30%) still costs about $16.5M in expected value.
B13: Beyond the DCF
B14: The case lists ESG benefits that cannot be modeled directly but matter given Liz's weak 2022 ESG rankings: social capital and trust, brand value, product differentiation, cost savings from reduced waste and carbon-pricing exposure, lower regulatory risk, and better employee retention.
B16: Recommendation
B17: Proceed with the project, but make green-bond financing a condition of approval, not a fallback; on these numbers it is what turns a marginal, DCF-negative project into a value-creating one. Given how close the base case sits to zero, the unquantified ESG benefits are the deciding factor that should tip a near coin-flip financial case toward acceptance. Anthony should present the board with the full range of outcomes above, not one point estimate, and flag green-bond financing, the CBAM tailwind, and rate/technology risk as the three things most worth acting on or monitoring.
