Workbook

Sheet Exhibit 1_Common stock data
B2: EXHIBIT 1: DOMINO'S PIZZA ENTERPRISES LIMITED COMMON STOCK
B3: SELECTED DATA 2000-2019
B5: Year | C5: Shares | D5: P/E | E5: EPS | F5: Dividend | G5: Dividend | H5: Opening Stock | I5: Closing Stock | J5: Total
C6: Outstanding | D6: Ratio | F6: Yield | G6: per | H6: Price Jan. 1 | I6: Price Dec. 31 | J6: Return
C7: (Million) | D7: (X) | F7: (%) | G7: Share (A$) | H7: (A$) | I7: (A$) | J7: (%)
B8: 2009 | C8: 69.71 | D8: 14.16 | E8: 0.23 | F8: 3.5 | G8: 0.12 | H8: 2.6242 | I8: 5.2678 | J8: 105.31
B9: 2010 | C9: 69.99 | D9: 20.84 | E9: 0.25 | F9: 2.56 | G9: 0.17 | H9: 5.2386 | I9: 6.1165 | J9: 20
B10: 2011 | C10: 70.12 | D10: 19.87 | E10: 0.29 | F10: 3.57 | G10: 0.21 | H10: 6.1165 | I10: 7.7067 | J10: 29.43
B11: 2012 | C11: 71.65 | D11: 25.84 | E11: 0.37 | F11: 2.44 | G11: 0.26 | H11: 7.6091 | I11: 10.243 | J11: 38.03
B12: 2013 | C12: 71.95 | D12: 29.57 | E12: 0.43 | F12: 6.48 | G12: 0.3 | H12: 10.243 | I12: 16.17 | J12: 60.79
B13: 2014 | C13: 85.93 | D13: 43.21 | E13: 0.54 | F13: 1.52 | G13: 0.37 | H13: 16.4 | I13: 25.2 | J13: 55.91
B14: 2015 | C14: 86.56 | D14: 48.73 | E14: 0.72 | F14: 1.21 | G14: 0.52 | H14: 25.23 | I14: 57.75 | J14: 130.96
B15: 2016 | C15: 87.65 | D15: 72.9 | E15: 1.02 | F15: 0.9 | G15: 0.74 | H15: 57.67 | I15: 64.99 | J15: 13.98
B16: 2017 | C16: 88.87 | D16: 44.9 | E16: 1.37 | F16: 1.67 | G16: 0.93 | H16: 65.35 | I16: 46.7 | J16: -27.12
B17: 2018 | C17: 85.37 | D17: 37.46 | E17: 1.57 | F17: 1.97 | G17: 1.08 | H17: 45.96 | I17: 40.65 | J17: -9.2
B18: 2019 | C18: 85.63 | D18: 27.78 | E18: 1.67 | F18: 2.99 | G18: 1.16 | H18: 40.7 | I18: 52.36 | J18: 31.5
B19: 2020 | C19: 86.23829 | D19: 42.131759 | E19: 1.713 | F19: 1.76 | G19: 1.72 | H19: 51.67 | I19: 84.73 | J19: 67.31
H21: Arithmetic Average | J21: =AVERAGE(J8:J19) -> 43.075
B23: Note: EPS = earnings per share; P/E = price earnings; total return = (Dividend + Price Change) ÷ Previous Price; A$ = AUD = Australian dollars; US$1 = A$1.3615 on November 30, 2020
B24: Source:
B25: Domino’s Pizza Enterprises Limited, “Dividend Summary,” Bloomberg LP, accessed January 24, 2021.
B26: Domino’s Pizza Enterprises Limited, “Adjusted Highlights,” Bloomberg LP, accessed January 24, 2021.
B27: Domino’s Pizza Enterprises Limited, “Stock Prices of Shares,” Bloomberg LP, accessed January 24, 2021.

Sheet Exhibit 2_Financial Ratio
B2: EXHIBIT 2: DOMINO'S PIZZA ENTERPRISES LIMITED FINANCIAL RATIOS
C4: FY 2015 | D4: FY 2016 | E4: FY 2017 | F4: FY 2018 | G4: FY 2019 | H4: FY 2020
B5: PROFITABILITY
B6: Return on Assets | C6: =C27 -> 0.10767914 | D6: =D27 -> 0.093739936 | E6: =E27 -> 0.090990701 | F6: =F27 -> 0.099758346 | G6: =G27 -> 0.084581839 | H6: =H27 -> 0.065563945
B7: Return on Equity | C7: =C31 -> 0.22259017 | D7: =D31 -> 0.26800909 | E7: =E31 -> 0.24833189 | F7: =F31 -> 0.42229955 | G7: =G31 -> 0.35162184 | H7: =H31 -> 0.41186201
B9: MARGIN ANALYSIS
B10: EBITDA Margin | C10: =1810.083%/100 -> 0.1810083 | D10: =1784.7529%/100 -> 0.17847529 | E10: =1873.8531%/100 -> 0.18738531 | F10: =2039.1114%/100 -> 0.20391114 | G10: =1616.8261%/100 -> 0.16168261 | H10: 0.1788
B11: EBIT Margin | C11: =1429.3084%/100 -> 0.14293084 | D11: =1390.2456%/100 -> 0.13902456 | E11: =1448.0117%/100 -> 0.14480117 | F11: =1596.3718%/100 -> 0.15963718 | G11: =1204.514%/100 -> 0.1204514 | H11: 0.1131
B12: Net Profit Margin | C12: ='[1]Exhibit 6 - Income Statement'!C28/'[1]Exhibit 6 - Income Statement'!C7 -> 0.091278726 | D12: ='[1]Exhibit 6 - Income Statement'!D28/'[1]Exhibit 6 - Income Statement'!D7 -> 0.088752573 | E12: ='[1]Exhibit 6 - Income Statement'!E28/'[1]Exhibit 6 - Income Statement'!E7 -> 0.096007983 | F12: ='[1]Exhibit 6 - Income Statement'!F28/'[1]Exhibit 6 - Income Statement'!F7 -> 0.10560406 | G12: ='[1]Exhibit 6 - Income Statement'!G28/'[1]Exhibit 6 - Income Statement'!G7 -> 0.081029351 | H12: ='[1]Exhibit 6 - Income Statement'!H28/'[1]Exhibit 6 - Income Statement'!H7 -> 0.072848828
B14: LIQUIDITY RATIOS
B15: Current Ratio | C15: 0.888783 | D15: 0.691962 | E15: 0.816112 | F15: 1.142028 | G15: 1.076418 | H15: 0.97
B16: Quick Ratio | C16: 0.62947 | D16: 0.469382 | E16: 0.507856 | F16: 0.764774 | G16: 0.781127 | H16: 0.78
B18: DEBT RATIOS
B19: Total Assets ÷ Total Equity | C19: ='[1]Exhibit 7 - Balance Sheet'!C18/'[1]Exhibit 7 - Balance Sheet'!C32 -> 2.0671614 | D19: ='[1]Exhibit 7 - Balance Sheet'!D18/'[1]Exhibit 7 - Balance Sheet'!D32 -> 2.8590706 | E19: ='[1]Exhibit 7 - Balance Sheet'!E18/'[1]Exhibit 7 - Balance Sheet'!E32 -> 2.7292008 | F19: ='[1]Exhibit 7 - Balance Sheet'!F18/'[1]Exhibit 7 - Balance Sheet'!F32 -> 4.2332252 | G19: ='[1]Exhibit 7 - Balance Sheet'!G18/'[1]Exhibit 7 - Balance Sheet'!G32 -> 4.1571789 | H19: ='[1]Exhibit 7 - Balance Sheet'!H18/'[1]Exhibit 7 - Balance Sheet'!H32 -> 6.2818368
B20: Total Liabilities ÷ Total Assets | C20: =19.79575/100 -> 0.1979575 | D20: =28.52685/100 -> 0.2852685 | E20: =29.064445/100 -> 0.29064445 | F20: =45.953159/100 -> 0.45953159 | G20: =45.289427/100 -> 0.45289427 | H20: 0.5586
B22: DuPONT ANALYSIS
B23: Net Profit Margin | C23: ='[1]Exhibit 6 - Income Statement'!C28/'[1]Exhibit 6 - Income Statement'!C7 -> 0.091278726 | D23: ='[1]Exhibit 6 - Income Statement'!D28/'[1]Exhibit 6 - Income Statement'!D7 -> 0.088752573 | E23: ='[1]Exhibit 6 - Income Statement'!E28/'[1]Exhibit 6 - Income Statement'!E7 -> 0.096007983 | F23: ='[1]Exhibit 6 - Income Statement'!F28/'[1]Exhibit 6 - Income Statement'!F7 -> 0.10560406 | G23: ='[1]Exhibit 6 - Income Statement'!G28/'[1]Exhibit 6 - Income Statement'!G7 -> 0.081029351 | H23: ='[1]Exhibit 6 - Income Statement'!H28/'[1]Exhibit 6 - Income Statement'!H7 -> 0.072848828
B24: ×
B25: Asset Turnover | C25: 1.179674 | D25: 1.056194 | E25: 0.947741 | F25: 0.944645 | G25: 1.043842 | H25: 0.9
B26: =
B27: Return on Assets | C27: =C23*C25 -> 0.10767914 | D27: =D23*D25 -> 0.093739936 | E27: =E23*E25 -> 0.090990701 | F27: =F23*F25 -> 0.099758346 | G27: =G23*G25 -> 0.084581839 | H27: =H23*H25 -> 0.065563945
B28: ×
B29: Equity Multiplier | C29: =C19 -> 2.0671614 | D29: =D19 -> 2.8590706 | E29: =E19 -> 2.7292008 | F29: =F19 -> 4.2332252 | G29: =G19 -> 4.1571789 | H29: =H19 -> 6.2818368
B30: =
B31: Return on Equity | C31: =C27*C29 -> 0.22259017 | D31: =D27*D29 -> 0.26800909 | E31: =E27*E29 -> 0.24833189 | F31: =F27*F29 -> 0.42229955 | G31: =G27*G29 -> 0.35162184 | H31: =H27*H29 -> 0.41186201
B33: Note: FY = fiscal year; EBITDA = earnings before interest, taxes, depreciation, and amortization;
B34: EBIT = earnings before interest and taxes
B35: Source:
B36: Domino’s Pizza Enterprises Limited, “Liquidity Ratios,” Bloomberg LP, accessed January 24, 2021.
B37: Domino’s Pizza Enterprises Limited, “Profitability Ratios,” Bloomberg LP, accessed January 24, 2021.
B38: Domino’s Pizza Enterprises Limited, “DuPont Analysis,” Bloomberg LP, accessed January 24, 2021.

Sheet Exhibit 3_ Debt
B2: EXHIBIT 3: DOMINO'S PIZZA ENTERPRISES LIMITED COST OF DEBT
B3: 2020 Annual Report
B5: Liability | C5: Interest Rate (%) | D5: Value (in A$ Thousand) | E5: Weight (%) | F5: Weight of Interest-Bearing Debt (%) | G5: Weighted Cost of Debt (%)
B6: Trade and Other Payables | C6: — | D6: 323618 | E6: =(D6/$D$17)*100 -> 16.575038 | F6: — | G6: —
B7: Other Financial Liabilities | C7: — | D7: 12269 | E7: =(D7/$D$17)*100 -> 0.62839255 | F7: — | G7: —
B8: Bank Loans | C8: 1.81 | D8: 621263 | E8: =(D8/$D$17)*100 -> 31.819793 | F8: =D8*100/($D$8+$D$9+$D$10+$D$16) -> 42.099888 | G8: =C8*F8/100 -> 0.76200798
B9: Other Bank Loans | C9: 0.77 | D9: 50195 | E9: =(D9/$D$17)*100 -> 2.570883 | F9: =D9*100/($D$8+$D$9+$D$10+$D$16) -> 3.4014643 | G9: =F9*C9/100 -> 0.026191275
B10: Loans from Other Entities | C10: 2.7 | D10: 35978 | E10: =(D10/$D$17)*100 -> 1.842718 | F10: =D10*100/($D$8+$D$9+$D$10+$D$16) -> 2.4380492 | G10: =F10*C10/100 -> 0.065827329
B11: Market Access Right | C11: — | D11: 24690 | E11: =(D11/$D$17)*100 -> 1.2645702 | F11: — | G11: —
B12: Put-Option Liability | C12: — | D12: 112980 | E12: =(D12/$D$17)*100 -> 5.7865996 | F12: — | G12: —
B13: Contingent Consideration | C13: — | D13: 633 | E13: =(D13/$D$17)*100 -> 0.032420937 | F13: — | G13: —
B14: Deferred Consideration | C14: — | D14: 1253 | E14: =(D14/$D$17)*100 -> 0.064176042 | F14: — | G14: —
B15: Interest Rates Swaps | C15: — | D15: 1311 | E15: =(D15/$D$17)*100 -> 0.067146681 | F15: — | G15: —
B16: Lease Liabilities* | C16: 0.97 | D16: 768252 | E16: =(D16/$D$17)*100 -> 39.348262 | F16: =D16*100/($D$8+$D$9+$D$10+$D$16) -> 52.060598 | G16: 0
B17: Total | D17: =SUM(D6:D16) -> 1952442 | G17: =SUM(G8:G16) -> 0.85402658
B19: Note: *Rental lease liability has increased materially as a result of IFRS 16 implementation and has not
B20: been included in the weighted cost of debt calculation.
B21: Source:
B22: Domino’s Pizza Enterprises Ltd., Annual Report 2020, accessed January 10, 2021,
B23: https://investors.dominos.com.au/s/FY20-Annual-Report-nj2r.pdf.

Sheet Exhibit 4_Treasury bond
D2: EXHIBIT 4: AUSTRALIAN GOVERNMENT TREASURY BOND YIELDS
D3: AS OF NOVEMBER 1, 2020
E5: Bond Duration | F5: Yield to Maturity
E6: 1 Year | F6: 0.0007
E7: 2 Years | F7: 0.0011
E8: 3 Years | F8: 0.0012
E9: 5 Years | F9: 0.0028
E10: 7 Years | F10: 0.0049
E11: 10 Years | F11: 0.0081
E12: 20 Years | F12: 0.0143
E13: 30 Years | F13: 0.0179
D15: Source: Australian Government, “Australian Government Treasury Bond Rates,” Bloomberg LP, accessed January 24, 2021.

Sheet Exhibit 5_Aggregate bond yield
B2: EXHIBIT 5: AVERAGE HISTORICAL AUSTRALIAN CORPORATE BOND SPREADS (%)
B3: AS OF FEBRUARY 27, 2020
B5: Rating | C5: Duration | D5: FY 2020 | E5: FY 2019 | F5: FY 2018 | G5: FY 2017 | H5: FY 2016 | I5: FY 2015
B6: A | C6: 3 years | D6: 0.0128 | E6: 0.0269 | F6: 0.0282 | G6: 0.0287 | H6: 0.0386 | I6: 0.0282
B7: BBB | C7: 3 years | D7: 0.0163 | E7: 0.0319 | F7: 0.0319 | G7: 0.0353 | H7: 0.0522 | I7: 0.0368
B8: A | C8: 5 years | D8: 0.014 | E8: 0.0292 | F8: 0.0313 | G8: 0.0323 | H8: 0.0408 | I8: 0.0316
B9: BBB | C9: 5 years | D9: 0.0181 | E9: 0.0351 | F9: 0.0354 | G9: 0.0385 | H9: 0.0555 | I9: 0.0396
B10: A | C10: 7 years | D10: 0.0164 | E10: 0.0325 | F10: 0.0346 | G10: 0.036 | H10: 0.0432 | I10: 0.0345
B11: BBB | C11: 7 years | D11: 0.068 | E11: 0.0684 | F11: 0.0688 | G11: 0.0678 | H11: 0.0659 | I11: 0.0662
B12: A | C12: 10 years | D12: 0.0182 | E12: 0.0325 | F12: 0.0346 | G12: 0.036 | H12: 0.0432 | I12: 0.0345
B13: BBB | C13: 10 years | D13: 0.025 | E13: 0.0432 | F13: 0.0429 | G13: 0.0463 | H13: 0.0557 | I13: 0.0437
B15: Note: FY = fiscal year.
B16: Source: “Aggregate Measures of Australian Corporate Bond Spreads 2005–2021,” Reserve Bank of Australia, accessed January 24, 2021.

Sheet Exhibit 6_Income statement
B2: EXHIBIT 6: DOMINO'S PIZZA ENTERPRISES LIMITED INCOME STATEMENT
B3: (IN A$ MILLIONS)
C5: FY 2015 | D5: FY 2016 | E5: FY 2017 | F5: FY 2018 | G5: FY 2019 | H5: FY 2020
B6: 12 Months Ending | C6: 06/28/2015 | D6: 07/03/2016 | E6: 07/02/2017 | F6: 07/01/2018 | G6: 06/30/2019 | H6: 06/28/2020
B7: Revenue | C7: 701.675 | D7: 928.728 | E7: 1071.338 | F7: 1150.202 | G7: 1430.494 | H7: 1900.964
B8: − Operating Expenses | C8: 608.521 | D8: 798.125 | E8: 907.136 | F8: 967.795 | G8: 1233.21 | H8: 1696.174
B9: + Selling, General, & Admin | C9: 43.733 | D9: — | E9: — | F9: — | G9: — | H9: —
B10: + Selling & Marketing | C10: 43.733 | D10: 48.251 | E10: 49.22 | F10: 49.704 | G10: 150.999 | H10: 181.842
B11: + Research & Development | C11: 0 | D11: 0 | E11: 0 | F11: 0 | G11: 0 | H11: 0
B12: + Depreciation & Amortization | C12: 27.48 | D12: 38.129 | E12: 46.369 | F12: 53.537 | G12: 62.785 | H12: 125.498
B13: + Other Operating Expense | C13: 537.308 | D13: 711.745 | E13: 811.547 | F13: 864.554 | G13: 1019.426 | H13: 1388.834
B14: Operating Income (Loss) | C14: 93.154 | D14: 130.701 | E14: 164.434 | F14: 183.857 | G14: 197.284 | H14: 204.79
B15: − Non-Operating (Income) Loss | C15: 1.689 | D15: 1.807 | E15: 3.704 | F15: 6.526 | G15: 9.088 | H15: 10.207
B16: + Interest Expense, Net | C16: 1.689 | D16: 1.807 | E16: 2.664 | F16: 5.389 | G16: 7.976 | H16: 6.934
B17: + Foreign Exch (Gain) Loss | C17: 0 | D17: 0 | E17: 0 | F17: 0 | G17: 0 | H17: 0
B18: + Other Non-Op (Income) Loss | C18: 0 | D18: 0 | E18: 1.04 | F18: 1.137 | G18: 1.112 | H18: 3.273
B19: Pre-Tax Income (Loss), Adjusted | C19: 91.465 | D19: 128.894 | E19: 160.73 | F19: 177.331 | G19: 188.196 | H19: 194.583
B20: − Abnormal Losses (Gains) | C20: -6.375 | D20: 3.075 | E20: 10.05 | F20: 2.855 | G20: 28.783 | H20: -8.853
B21: + Merger/Acquisition Expense | C21: — | D21: 12.735 | E21: 28.384 | F21: 20.934 | G21: 46.216 | H21: —
B22: + Disposal of Assets | C22: -6.375 | D22: -9.66 | E22: -18.334 | F22: -18.079 | G22: — | H22: -21.27
B23: Pre-Tax Income (Loss), GAAP | C23: 97.84 | D23: 125.819 | E23: 150.68 | F23: 174.476 | G23: 159.413 | H23: 203.436
B24: − Income Tax Expense (Benefit) | C24: 29.419 | D24: 39.227 | E24: 44.876 | F24: 52.783 | G24: 45.034 | H24: 60.515
B25: + Current Income Tax | C25: 29.278 | D25: 28.467 | E25: 31.837 | F25: 46.335 | G25: 49.773 | H25: 55.351
B26: + Deferred Income Tax | C26: 0.141 | D26: 10.999 | E26: 11.943 | F26: 7.284 | G26: -5.069 | H26: 4.93
B27: + Tax Allowance/Credit | C27: — | D27: -0.239 | E27: 1.096 | F27: -0.836 | G27: 0.33 | H27: 0.234
B28: Net Income, GAAP | C28: 64.048 | D28: 82.427 | E28: 102.857 | F28: 121.466 | G28: 115.912 | H28: 138.483
B29: Diluted EPS, GAPP | C29: 0.728 | D29: 0.922 | E29: 1.147 | F29: 1.39 | G29: 1.354 | H29: 1.608
B30: Dividends per Share | C30: 0.518 | D30: 0.735 | E30: 0.933 | F30: 1.078 | G30: 1.155 | H30: 1.723
B31: Effective Tax Rate | C31: 30.068479 | D31: 31.177326 | E31: 29.78232 | F31: 30.252298 | G31: 28.249892 | H31: 34.59
B33: Note: This balance sheet was simplified for ease of discussion. GAAP = generally accepted accounting principles; EPS = earnings per share
B34: Source:
B35: Domino’s Pizza Enterprises Limited, “Adjusted Income Statement,” Bloomberg LP, accessed January 24, 2021.

Sheet Exhibit 7_Balance sheet
B2: EXHIBIT 7: DOMINO'S PIZZA ENTERPRISES LIMITED BALANCE SHEET
B3: (IN A$ MILLIONS)
C5: FY 2015 | D5: FY 2016 | E5: FY 2017 | F5: FY 2018 | G5: FY 2019 | H5: FY2020
B6: 12 Months Ending | C6: 06/28/2015 | D6: 07/03/2016 | E6: 07/02/2017 | F6: 07/01/2018 | G6: 06/30/2019 | H6: 06/28/2020
B7: Assets
B8: + Cash, Cash Equivalents, & ST Inv | C8: 43.174 | D8: 60.334 | E8: 50.454 | F8: 75.996 | G8: 101.404 | H8: 245.678
B9: + Accounts Receivable | C9: 39.369 | D9: 64.639 | E9: 66.427 | F9: 77.758 | G9: 91.122 | H9: 188.622
B10: + Inventories | C10: 12.282 | D10: 16.675 | E10: 21.098 | F10: 19.271 | G10: 22.11 | H10: 27.912
B11: + Other ST Assets | C11: 21.722 | D11: 42.587 | E11: 49.846 | F11: 56.574 | G11: 50.671 | H11: 60.187
B12: Total Current Assets | C12: =SUM(C8:C11) -> 116.547 | D12: =SUM(D8:D11) -> 184.235 | E12: =SUM(E8:E11) -> 187.825 | F12: =SUM(F8:F11) -> 229.599 | G12: =SUM(G8:G11) -> 265.307 | H12: =SUM(H8:H11) -> 522.399
B14: + Property, Plant, & Equip, Net | C14: 121.612 | D14: 188.05 | E14: 198.674 | F14: 200.103 | G14: 253.152 | H14: 651.83
B15: + LT Investments & Receivables | C15: 0 | D15: 0 | E15: 0 | F15: 0 | G15: 0 | H15: 333.834
B16: + Other LT Assets | C16: 392.441 | D16: 755.747 | E16: 746.294 | F16: 872.709 | G16: 919.954 | H16: 963.042
B17: Total Noncurrent Assets | C17: =SUM(C14:C16) -> 514.053 | D17: =SUM(D14:D16) -> 943.797 | E17: =SUM(E14:E16) -> 944.968 | F17: =SUM(F14:F16) -> 1072.812 | G17: =SUM(G14:G16) -> 1173.106 | H17: =SUM(H14:H16) -> 1948.706
B18: Total Assets | C18: =SUM(C12+C17) -> 630.6 | D18: =SUM(D12+D17) -> 1128.032 | E18: =SUM(E12+E17) -> 1132.793 | F18: =SUM(F12+F17) -> 1302.411 | G18: =SUM(G12+G17) -> 1438.413 | H18: =SUM(H12+H17) -> 2471.105
B20: Liabilities & Shareholders' Equity
B21: + Payables & Accruals | C21: 85.763 | D21: 92.16 | E21: 93.236 | F21: 117.569 | G21: 151.814 | H21: 254.297
B22: + ST Debt | C22: 1.92 | D22: 36.285 | E22: 17.91 | F22: 3.7 | G22: 5.373 | H22: 155.398
B23: Total Current Liabilities | C23: =SUM(C21:C22) -> 87.683 | D23: =SUM(D21:D22) -> 128.445 | E23: =SUM(E21:E22) -> 111.146 | F23: =SUM(F21:F22) -> 121.269 | G23: =SUM(G21:G22) -> 157.187 | H23: =SUM(H21:H22) -> 409.695
B25: + LT Debt | C25: 122.912 | D25: 285.507 | E25: 311.33 | F25: 594.799 | G25: 646.076 | H25: 1320.29
B26: Total Noncurrent Liabilities | C26: =SUM(C25:C25) -> 122.912 | D26: =SUM(D25:D25) -> 285.507 | E26: =SUM(E25:E25) -> 311.33 | F26: =SUM(F25:F25) -> 594.799 | G26: =SUM(G25:G25) -> 646.076 | H26: =SUM(H25:H25) -> 1320.29
B27: Total Liabilities | C27: =SUM(C23+C26) -> 210.595 | D27: =SUM(D23+D26) -> 413.952 | E27: =SUM(E23+E26) -> 422.476 | F27: =SUM(F23+F26) -> 716.068 | G27: =SUM(G23+G26) -> 803.263 | H27: 2077.732
B29: + Common Stock | C29: 198.291 | D29: 198.291 | E29: 198.291 | F29: 198.291 | G29: 198.291 | H29: 198.291
B30: + Retained Earnings | C30: 106.375 | D30: 134.798 | E30: 160.569 | F30: 191.227 | G30: 197.06 | H30: 227.969
B31: + Other Equity | C31: 0.39 | D31: 11.193 | E31: -85.545 | F31: -76.371 | G31: -57.271 | H31: -70.016
B32: Total Equity | C32: 305.056 | D32: 394.545 | E32: 415.064 | F32: 307.664 | G32: 346.007 | H32: 393.373
B33: Total Liabilities & Equity | C33: =SUM(C27+C32) -> 515.651 | D33: =SUM(D27+D32) -> 808.497 | E33: =SUM(E27+E32) -> 837.54 | F33: =SUM(F27+F32) -> 1023.732 | G33: =SUM(G27+G32) -> 1149.27 | H33: =SUM(H27+H32) -> 2471.105
B35: Note: This balance sheet was simplified for ease of discussion. ST = short-term; Inv = investments; Equip = equipment; LT = long-term.
B36: Source:
B37: Domino’s Pizza Enterprises Limited, “Adjusted Balance Sheet,” Bloomberg LP, accessed January 24, 2021.

Sheet Exhibit 8_Peer firm
B2: EXHIBIT 8: DOMINO'S PIZZA ENTERPRISES LIMITED COMPARABLE FIRM DATA
B3: AS OF NOVEMBER 1, 2020 (US$ MILLIONS)
C5: KFC Holdings | D5: McDonald's | E5: Restaurant Brands | F5: Matsuya Foods | G5: Yoshino
B6: Financial Summary | C6: Japan | D6: Corp Japan | E6: New Zealand | F6: Holding Co Ltd | G6: Co Ltd
B7: Revenue | C7: 1075.6 | D7: 3719.8 | E7: 768.5 | F7: 1438.7 | G7: 2879.8
B8: Book Value of Equity | C8: 331.6 | D8: 2088.7 | E8: 215.5 | F8: 653.1 | G8: 689.3
B9: Book Value of Debt | C9: 246.4 | D9: 818.2 | E9: 226 | F9: 459.5 | G9: 1108.1
B11: Market Data
B12: Beta | C12: 0.43 | D12: 0.515 | E12: 0.716 | F12: 0.579 | G12: 0.579
B13: Shares Outstanding (Million) | C13: 24.42 | D13: 133 | E13: 124.8 | F13: 19.1 | G13: 64.6
B14: Share Price (November 1, 2020) | C14: 2520 | D14: 5000 | E14: 11.99 | F14: 3450 | G14: 1912
B15: Dividend per Share | C15: 0.68 | D15: 0.44 | E15: 0 | F15: 0.32 | G15: 0.13
B17: Source:
B18: Domino’s Pizza Enterprises Limited, “KFC Holdings Japan, Common Stock Data,” Bloomberg LP, accessed January 24, 2021.
B19: Domino’s Pizza Enterprises Limited, “McDonalds Japan, Common Stock Data,” Bloomberg LP, accessed January 24, 2021.
B20: Domino’s Pizza Enterprises Limited, “Restaurant Brands New Zealand, Common Stock Data,” Bloomberg LP, accessed January 24, 2021.
B21: Domino’s Pizza Enterprises Limited, “Matsuya Foods, Common Stock Data,” Bloomberg LP, accessed January 24, 2021.
B22: Domino’s Pizza Enterprises Limited, “Yoshino Food, Common Stock Data,” Bloomberg LP, accessed January 24, 2021.

Sheet Assumptions for Answers
B2: KEY ASSUMPTIONS USED IN THIS SUBMISSION
B5: 1. Risk-free rate | C5: 10-year Australian Government Treasury bond yield as of Nov 1, 2020 (0.81%, Exhibit 4) is used as the proxy for the risk-free rate. A longer-tenor bond is preferred over the 1-year rate because the short end of the curve was temporarily distorted by the RBA's emergency 0.10% cash-rate cut and COVID-19 quantitative easing, making it an unreliable long-run proxy.
B7: 2. Equity beta | C7: The Team was given four beta estimates: raw 5-yr beta (0.85 low / 0.95 high) and adjusted 5-yr beta (0.94 low / 1.07 high). In the absence of a single 'correct' figure, the simple average of all four estimates, 0.9525 (≈0.95), is used as a representative point estimate for CAPM.
B9: 3. Market risk premium (MRP) | C9: 6.25%, the Bloomberg-reported Australian MRP for 2020, is used instead of the generic 4-5% global average cited in the case, since it is specific to DPE's primary listing market.
B11: 4. Corporate tax rate | C11: 30% is used, close to both DPE's average effective tax rate for FY2016-FY2019 (about 29.9%, treating the FY2020 rate of 34.59% as an outlier distorted by COVID-19 abnormal items) and the Australian statutory company tax rate.
B13: 5. Cost of debt - method used | C13: A forward-looking 'bond build-up' approach (risk-free rate + credit spread) is used as the primary cost of debt, because the Team is estimating the cost of capital for 2021 investment planning, not merely reporting the historical book cost of existing loans. DPE carries no public credit rating, so a synthetic BBB rating is assumed given its FY2020 total-liabilities-to-total-assets ratio of ~56% (moderate/rising leverage) and mid-single-digit EBIT margins. The BBB 10-year spread for FY2020 (2.50%, Exhibit 5) is added to the 10-year risk-free rate. The existing weighted book cost of debt (0.85%, Exhibit 3) is retained in the workbook as a historical cross-check.
B15: 6. Lease liabilities (IFRS 16) | C15: Lease liabilities are excluded from both the cost of debt calculation and the book value of debt used for capital-structure weights, consistent with the case's own note that IFRS 16 lease liabilities distort the debt figures and were excluded from the FY2020 weighted cost of debt calculation.
B17: 7. Market value of debt | C17: No market price is available for DPE's private bank loans and other borrowings, so, as is standard when a debt instrument is not publicly traded, the market value of debt is assumed to equal its book (interest-bearing) value: Bank Loans plus Other Bank Loans plus Loans from Other Entities, A$707.4 million (Exhibit 3).
B19: 8. Market value of equity | C19: 86.24 million shares outstanding × A$84.70 share price, both taken directly from the case narrative (as of Nov 1, 2020) = A$7,304.5 million.
B21: 9. Book value of equity | C21: Total Shareholders' Equity, FY2020 (Exhibit 7) = A$393.4 million.
B23: 10. Dividend Discount Model (DDM) cross-check | C23: The Dividend Discount Model (Re = D1/P0 + g) is used only as a cross-check for the cost of equity, not the primary method. DPE's historical dividend growth (roughly 27% a year from 2009 to 2020) is far too high to use as a perpetual growth rate, since it would imply g greater than Ke and break the Gordon Growth Model's own logic. A conservative 3% long-run growth rate is used for that cross-check only, roughly in line with long-term nominal GDP growth. CAPM stays the primary method, matching the case's own point that about 85% of firms and close to 100% of financial advisers surveyed use CAPM or a modified version of it.
B25: 11. Target/industry capital structure | C25: The case states DPE's target and industry-average debt-to-equity ratio is 18%, used directly for the 'target' WACC scenario.

Sheet Q2 - Cost of Debt
B2: COST OF DEBT (Kd)
B4: Method A: historical / book cost of existing debt (cross-check, FY2020)
B5: Weighted cost of existing interest-bearing debt (pre-tax) | C5: ='Exhibit 3_ Debt'!G17 -> 0.85402658
B6: Assumed corporate tax rate | C6: 0.3
B7: After-tax cost of debt (Method A) | C7: =C5*(1-C6) -> 0.59781861
B9: Method B: forward-looking bond build-up method (primary method used)
B10: Risk-free rate (10-yr Australian Govt Treasury bond, Nov 1, 2020) | C10: ='Exhibit 4_Treasury bond'!F11 -> 0.0081 | D10: Reference in - Assumptions tab (#1, #5)
B11: Assumed credit rating (synthetic, no public rating available) | C11: BBB
B12: Credit spread (BBB, 10-year, FY2020, Exhibit 5) | C12: ='Exhibit 5_Aggregate bond yield'!D13 -> 0.025
B13: Pre-tax cost of debt (Kd) = Risk-free rate + Credit spread | C13: =C10+C12 -> 0.0331
B14: Assumed corporate tax rate | C14: 0.3
B15: After-tax cost of debt, Kd x (1-T), used in WACC | C15: =C13*(1-C14) -> 0.02317
B17: SUMMARY
B18: Method | C18: Pre-tax Kd | D18: After-tax Kd | E18: Basis
B19: A. Historical / book (existing loans) | C19: =C5 -> 0.85402658 | D19: =C7 -> 0.59781861 | E19: Exhibit 3 weighted cost of debt
B20: B. Forward-looking build-up (used in WACC) | C20: =C13 -> 0.0331 | D20: =C15 -> 0.02317 | E20: 10-yr Rf + BBB credit spread

Sheet Q3 - Cost of Equity
B2: COST OF EQUITY (Ke)
B4: Primary method: CAPM, Ke = Rf + Beta x MRP
B5: Risk-free rate (10-yr Australian Govt Treasury bond) | C5: ='Exhibit 4_Treasury bond'!F11 -> 0.0081
B6: Beta: raw 5-yr, low | C6: 0.85 | D6: 4 beta figures given in case narrative; Reference in - Assumptions tab #2.
B7: Beta: raw 5-yr, high | C7: 0.95
B8: Beta: adjusted 5-yr, low | C8: 0.94
B9: Beta: adjusted 5-yr, high | C9: 1.07
B10: Beta used (average of the four estimates) | C10: =AVERAGE(C6:C9) -> 0.9525
B11: Market risk premium (MRP), Bloomberg Australia, 2020 | C11: 0.0625
B12: Cost of equity (Ke), CAPM | C12: =C5+C10*C11 -> 0.06763125
B14: Cross-check: Dividend Discount Model (Gordon Growth), Ke = D1/P0 + g
B15: Current dividend per share, D0 (FY2020, Exhibit 1 / case narrative) | C15: 1.72 | D15: Historical dividend CAGR (2009-2020, Exhibit 1) is about 27% a year, far too high to use as a perpetual growth rate. A conservative 3% is substituted here for illustrative cross-check purposes only.
B16: Assumed sustainable long-run growth rate, g (see Assumptions #10) | C16: 0.03
B17: Expected dividend next period, D1 = D0 × (1+g) | C17: =C15*(1+C16) -> 1.7716
B18: Current share price, P0 (Nov 2020, case narrative) | C18: 84.7
B19: Cost of equity (Ke), DDM cross-check | C19: =C17/C18+C16 -> 0.050916175
B21: SELECTED COST OF EQUITY (used in WACC)
B22: Ke used | C22: =C12 -> 0.06763125

Sheet Q4a - WACC - Book Value
B2: WACC: BOOK VALUE WEIGHTS
B4: CAPITAL STRUCTURE (BOOK VALUES, FY2020, A$ MILLION)
B5: Book value of debt: Bank Loans | C5: ='Exhibit 3_ Debt'!D8/1000 -> 621.263 | D5: Excludes lease liabilities (IFRS 16). Reference in - Assumptions #6.
B6: Book value of debt: Other Bank Loans | C6: ='Exhibit 3_ Debt'!D9/1000 -> 50.195
B7: Book value of debt: Loans from Other Entities | C7: ='Exhibit 3_ Debt'!D10/1000 -> 35.978
B8: Total book value of interest-bearing debt (excl. lease liabilities) | C8: =SUM(C5:C7) -> 707.436
B9: Book value of equity (Total Shareholders' Equity, FY2020) | C9: ='Exhibit 7_Balance sheet'!H32 -> 393.373
B10: Total book value of capital (D + E) | C10: =C8+C9 -> 1100.809
B12: WEIGHTS
B13: Weight of debt = D / (D+E) | C13: =C8/C10 -> 0.642651
B14: Weight of equity = E / (D+E) | C14: =C9/C10 -> 0.357349
B16: COMPONENT COSTS
B17: After-tax cost of debt, Kd(1-T) | C17: ='Q2 - Cost of Debt'!C15 -> 0.02317
B18: Cost of equity, Ke | C18: ='Q3 - Cost of Equity'!C22 -> 0.06763125
B20: WACC (BOOK VALUE)
B21: WACC = Wd × Kd(1-T) + We × Ke | C21: =C13*C17+C14*C18 -> 0.039058183

Sheet Q4b - WACC - Market Value
B2: WACC: MARKET VALUE WEIGHTS
B4: CAPITAL STRUCTURE (MARKET VALUES, NOV 2020, A$ MILLION)
B5: Shares outstanding (million) | C5: 86.24
B6: Share price, Nov 2020 (A$) | C6: 84.7
B7: Market value of equity = Shares × Price | C7: =C5*C6 -> 7304.528
B8: Market value of debt (assumed = book value of interest-bearing debt) | C8: ='Q4a - WACC - Book Value'!C8 -> 707.436
B9: Total market value of capital (D + E) | C9: =C7+C8 -> 8011.964
B11: WEIGHTS
B12: Weight of debt = D / (D+E) | C12: =C8/C9 -> 0.088297451
B13: Weight of equity = E / (D+E) | C13: =C7/C9 -> 0.91170255
B15: COMPONENT COSTS
B16: After-tax cost of debt, Kd(1-T) | C16: ='Q2 - Cost of Debt'!C15 -> 0.02317
B17: Cost of equity, Ke | C17: ='Q3 - Cost of Equity'!C22 -> 0.06763125
B19: WACC (MARKET VALUE)
B20: WACC = Wd × Kd(1-T) + We × Ke | C20: =C12*C16+C13*C17 -> 0.063705435

Sheet Q4c - Scenario - Target DE 18%
B2: SCENARIO: TARGET DEBT-TO-EQUITY RATIO OF 18%
B5: TARGET CAPITAL STRUCTURE
B6: Target D/E ratio | C6: 0.18
B7: Weight of debt = (D/E) / (1 + D/E) | C7: =C6/(1+C6) -> 0.15254237
B8: Weight of equity = 1 / (1 + D/E) | C8: =1/(1+C6) -> 0.84745763
B10: COMPONENT COSTS
B11: After-tax cost of debt, Kd(1-T) | C11: ='Q2 - Cost of Debt'!C15 -> 0.02317
B12: Cost of equity, Ke | C12: ='Q3 - Cost of Equity'!C22 -> 0.06763125
B14: WACC (TARGET STRUCTURE)
B15: WACC = Wd × Kd(1-T) + We × Ke | C15: =C7*C11+C8*C12 -> 0.060849025

Sheet Q4d - Scenario Summary
B2: SCENARIO SUMMARY: LOW, HIGH & ACTUAL WEIGHTS OF DEBT AND EQUITY
B3: 3 internally consistent weighting bases are compared below, spanning the realistic range of DPE's capital structure.
B5: Scenario | C5: Basis | D5: Weight of Debt | E5: Weight of Equity | F5: Kd (after-tax) | G5: Ke | H5: WACC
B6: Low debt weight | C6: Market value weights (equity valued at market price) | D6: ='Q4b - WACC - Market Value'!C12 -> 0.088297451 | E6: ='Q4b - WACC - Market Value'!C13 -> 0.91170255 | F6: ='Q2 - Cost of Debt'!C15 -> 0.02317 | G6: ='Q3 - Cost of Equity'!C22 -> 0.06763125 | H6: ='Q4b - WACC - Market Value'!C20 -> 0.063705435
B7: Actual / target weight | C7: Company's target & industry-average D/E of 18% | D7: ='Q4c - Scenario - Target DE 18%'!C7 -> 0.15254237 | E7: ='Q4c - Scenario - Target DE 18%'!C8 -> 0.84745763 | F7: ='Q2 - Cost of Debt'!C15 -> 0.02317 | G7: ='Q3 - Cost of Equity'!C22 -> 0.06763125 | H7: ='Q4c - Scenario - Target DE 18%'!C15 -> 0.060849025
B8: High debt weight | C8: Book value weights (equity valued at accounting book value) | D8: ='Q4a - WACC - Book Value'!C13 -> 0.642651 | E8: ='Q4a - WACC - Book Value'!C14 -> 0.357349 | F8: ='Q2 - Cost of Debt'!C15 -> 0.02317 | G8: ='Q3 - Cost of Equity'!C22 -> 0.06763125 | H8: ='Q4a - WACC - Book Value'!C21 -> 0.039058183
B11: INTERPRETATION
B12: The after-tax cost of debt here (about 2.3%) sits far below the cost of equity (about 6.8%), a direct result of the ultra-low interest rates that followed the RBA's pandemic rate cuts. That is why WACC falls as the debt weight rises across these three scenarios: about 6.4% at market value (low debt) weights, about 6.1% at the 18% target D/E, and about 3.9% at book value (high debt) weights. This is a snapshot effect of unusually cheap debt in November 2020, not a general rule. It ignores that raising leverage further would likely push up DPE's equity beta, and therefore Ke, and could pressure its credit spread, and therefore Kd, if leverage rose enough to threaten its assumed BBB profile. The market value WACC (about 6.4%) is the most defensible single figure for evaluating new projects, since equity investors price their required return off the market value of their claim, not its book value. The book value WACC is included mainly as a lower-bound cross-check.

Sheet All Answers for the Case
B2: CASE DISCUSSION QUESTIONS: WRITTEN ANSWERS
B4: Q1. What is the cost of capital, and why is it important?
B5: The cost of capital is the minimum return a firm must earn on its investments to compensate everyone who supplies it money, lenders and shareholders alike, each bearing a different kind of risk. In practice it is the discount rate used to judge whether a project creates value: a project that earns more than the cost of capital adds to shareholder wealth (a positive NPV), while one that earns less destroys it. For DPE this is not an abstract exercise. The firm invests around A$99 million a year across nine countries, and the case itself points out that a difference of only a few percentage points in the cost of capital can shift capital spending by millions of dollars. Getting the estimate right matters directly for how DPE plans its 2021 investments, during a stretch when COVID-19 has made most of its usual assumptions less certain than normal.
B7: Q2. How should Coney estimate the cost of debt?
B8: Coney's team should be careful about taking the book cost of DPE's existing loans (a weighted 0.85%, per Exhibit 3) at face value, since that number reflects rates locked in when the debt was originally taken out, not what it would cost to borrow today. By November 2020 the RBA had just cut the cash rate to a record 0.10% and government bond yields had fallen sharply, so a forward-looking estimate makes more sense for 2021 planning. The usual approach is to start with a long-tenor government bond yield as the risk-free base (the case points to the 10-year or 30-year rate, since the 1-year rate was distorted by emergency stimulus) and add a credit spread that matches DPE's likely credit quality; Exhibit 5 gives spreads by rating and tenor. DPE has no public credit rating, so the team has to assume a reasonable synthetic one based on its leverage, coverage, and margins. This submission uses the 10-year yield of 0.81% plus a BBB spread of 2.50%, for a pre-tax cost of debt of 3.31%. Because interest is tax deductible, that figure is then multiplied by (1- tax rate) to get the after-tax cost of debt used in WACC, which works out to 2.32% at an assumed 30% tax rate. Lease liabilities under IFRS 16 are left out of the calculation, since the case notes they distort the figures.
B10: Q3. How should Coney estimate the cost of equity?
B11: CAPM (Ke = Rf + Beta x MRP) is the right primary method here, since the case notes that around 85% of leading corporations and virtually all financial advisers surveyed use CAPM or some modified version of it. That requires three inputs. First, a risk-free rate: again the 10-year government bond yield (0.81%) rather than the 1-year rate, for the same reasons as under cost of debt. Second, a beta: DPE was given four different estimates (raw and adjusted, each with a low and high figure), and since none of them is obviously the correct one, averaging all four to about 0.95 gives a reasonable single estimate, though a sensitivity range could just as easily be shown instead. Third, a market risk premium: the Bloomberg Australian MRP of 6.25% fits better than the generic 4-5% global average the case mentions, because it is specific to DPE's home market. Together these give a cost of equity of roughly 6.8%. A dividend discount model check (Ke = D1/P0 + g) is possible using DPE's dividend history in Exhibit 1, but the company's historical dividend growth, close to 27% a year, is nowhere near sustainable as a perpetuity assumption. It only works as a rough sanity check once the growth rate is scaled down heavily, not as the primary estimate.
B13: Q4. What is the WACC of Domino's Pizza?
B14: Using market values for the capital structure (equity worth roughly A$7,305 million at its November 2020 market price against about A$707 million of interest-bearing debt, or roughly 91% equity and 9% debt), an after-tax cost of debt near 2.3% and a CAPM cost of equity near 6.8%, DPE's WACC comes out to about 6.4%. On a book value basis, using accounting equity of about A$393 million against the same debt (roughly 36% equity, 64% debt), WACC drops to about 3.9%, because book equity is so much smaller relative to debt than market equity is. At the company's own stated target D/E ratio of 18%, WACC lands around 6.1%. The market value figure of about 6.4% is the one worth using for new investment decisions, since it reflects what investors currently require given how the market actually prices DPE, not what its accounting books happen to say.
B16: Q4a and Q4b. Book value WACC and market value WACC
B17: The full step-by-step math for both is in the 'Q4a - WACC - Book Value' and 'Q4b - WACC - Market Value' tabs. Book value WACC comes out to about 3.90%; market value WACC to about 6.37%, both built from the same cost of debt and cost of equity figures on the 'Q2 - Cost of Debt' and 'Q3 - Cost of Equity' tabs.
B19: Q4c. Scenario at a debt-to-equity ratio of 18%
... B29: DPE's WACC estimate turns out to be very sensitive to two things: whether book or market values are used to weight debt and equity, and the unusual, pandemic-driven collapse in risk-free rates through late 2020, which has pushed the after-tax cost of debt (about 2.3%) well below the cost of equity (about 6.8%). That combination produces a wide range of possible WACC figures, from about 3.9% to about 6.4%, depending purely on which capital structure assumption is used. For 2021 planning, the market value WACC of about 6.4% is the one to use as the primary hurdle rate, since it reflects what equity and debt investors actually require given how the market currently prices DPE. It is worth remembering this is a snapshot, not a fixed number. As rates normalize after COVID-19, and if DPE keeps adding leverage the way it has since 2010 (its debt-to-assets ratio climbed from 9.39% to 55.86% over that decade), both Kd and Ke are likely to shift, and the WACC estimate should be revisited rather than treated as permanent.
